{
  "ano": 2026,
  "igreja": "IBPS Muriaé",
  "pastores": [
    "Nélio Monteiro",
    "Ryan Sousa",
    "Gabriel Monteiro"
  ],
  "total_pregacoes": 7,
  "pregacoes": [
    {
      "id_original": 1,
      "titulo": "Ano Novo - Olhe para o Mestre!",
      "data_pregacao": "11/01/2026",
      "ano": 2026,
      "pregador": "Gabriel Monteiro",
      "tipo_pregador": "oficial",
      "conteudo_original": "Resenha do Culto da noite de Domingo\n11/01/2026\n\" Ano Novo - Olhe para o Mestre \"\nGuarde isso no seu coração:\n\"Quando estamos próximos de Jesus as impossibilidades se tornam possibilidades. Porque nada é impossível para Aquele que criou todas as coisas.\"\nMateus 14:22-27\nAo olhar para esse texto, a primeira pergunta a nos fazer é:\nPor que Jesus não acompanha os seus discípulos?\nPor que Jesus, de repente, precisa ficar só?\nO próprio texto nos informa essa resposta.\nPorque Jesus precisava de orar.\nPorque Jesus precisava de tempo a sós com o Pai. Porque Jesus precisava regar o relacionamento com o Pai.\nMesmo sendo Deus encarnado.\nMesmo sendo Aquele que criou todas as coisas.\nNo estado de humilhação, isto é, em que Cristo Jesus se torna homem, Ele nos ensina a importância da comunhão com o Pai.\nOração não é um capricho religioso.\nA oração deve ser um movimento de um coração que compreende, que as impossibilidades das nossas mãos, são possibilidades nas mãos de Deus.\nA oração coloca os joelhos dos homens, que muitas vezes se acham verdadeiros deuses, dobrados em humilhação, sobre o reconhecimento de quem Deus é.\nO crente que não ora, é o crente que não aprendeu a se deleitar na presença de Deus.\nMuitas vezes, a oração começa como uma disciplina, mas ela tem que se  transformar, em prazer, de estar em comunhão com Aquele, que pode o que não podemos.\nAqueles que não amam a presença de Deus nessa terra, o que querem fazer no céu?\nA oração é fundamental para manter-nos, de pé.\nSe o Próprio Cristo precisava de oração e de um tempo a sós com o Pai, quem dirá nós?!\nJESUS retirava-se das multidões.\nJesus direcionava-se a um lugar só.\nPorque a oração, deve ser algo que nos leva, completamente entregues à presença de um Deus, que não apenas escuta o que precisamos, mas que devemos entrar, em espírito de adoração e sede, pela presença do grande EU SOU.\nMateus 6:6\nComo será sua vida de oração, em 2026?\nOlhe para Jesus e você viverá tempos extraordinários, diante de Deus.\nO texto nos aponta para o movimento de Jesus ao encontro daqueles homens.\nEle termina de orar e de repente, Ele vai ao encontro daqueles que O esperam.\nA situação daqueles discípulos, que aguardam o Mestre, é complicada.\nUma tempestade se estabelece sobre a vida daqueles que seguem a Jesus.\nO barco está sendo levado de um lado para o outro.\nImagine o que se passava no coração daqueles homens, que deixaram o Mestre para trás!\nA tempestade recai sobre a vida dos seguidores de Jesus.\nCaminhar com Jesus não significa viver em meio ao mar tranquilo.\nCaminhar com Jesus não significa que as ondas deixarão de bater na sua casa.\nCaminhar com Jesus, não significa que você será livrado de todas as provações dessa terra.\nCristo não nos promete águas tranquilas.\nA vida, por muitos momentos,  nos sacode de um lado para o outro.\nExistem momentos, que seremos nós, dentro do barco.\nMas existe algo, que não pode sair do coração daquele que crê - que Jesus está vindo ao seu encontro.\nAqueles discípulos estão em meio a tempestade, mas Jesus está vindo ao seu encontro.\nAs tempestades da vida tendem, em muitos momentos, nos fazer  esquecer que Jesus está vindo ao nosso encontro.\nNão desista!\nAqueles que temem a Jesus, de maneira nenhuma serão desamparados.\nO texto nos diz que era alta madrugada. Estamos em um momento em que a tempestade se inside.\nA quarta vigília da noite, é o momento mais escuro da madrugada.\nNaquele momento não há mais recurso marítimo.\nA desesperança começa a bater à porta.\n\"O que será de nós, que estamos aqui nesse mar?\"\n\"Será que Jesus nos tirou daquele lugar de rotina, para nos trazer ao mar revolto e tirar a nossa vida?\"\nO que se passa no seu coração, nos momentos de dor?\nDeus não se esqueceu de você!\nDeus não está indiferente a sua dor!\nPor muitos momentos, a caminhada do Mestre até você, demora um tempo. Ele está ensinando você, sobre ter fé. Sobre perseverar em meio às provações.\nAs tempestades da vida, nem sempre vem para destruir a sua história.\nMuitas vezes, elas vêm, para afiar o seu coração, transbordar a graça de Deus  e te fazer mais parecido com Jesus.\nNaquele momento, na alta madrugada - \"De onde me virá o socorro?\"\nEis que vem uma figura distante.\n\" É um fantasma! \"\nGritam com muito medo.\nNa cultura judaica, acreditava-se que onde as pessoas morriam, a alma ficava por algum tempo ali.\n\"Estamos vendo uma assombração?\"\nJesus vem andando sobre as águas.\nA fala de Jesus para aqueles homens é a mesma para cada um de nós.\n\"Coragem! Sou Eu. Não tenham medo.\"\nEssa é a voz do Senhor para conosco.\nExistem momentos que precisamos abrir nossos ouvidos, em meio ao caos, para ouvir Jesus dizendo:\n\"Coragem!\"\nNesse momento, a tempestade não cessa. A calmaria não vem.\nEm meio aquele caos, Jesus os convida a olhar para Ele.\nE Ele diz:\n\"Coragem! Sou Eu. Não tenham medo.\"\nA calmaria não ocorre de imediato. Mas isso não importava mais.\nSó compreendemos momentos como esses, quando estamos imersos nas tempestades da vida.\nQuando não encontramos solução, de repente se apresenta, Cristo Jesus, andando sobre as águas. E Ele olha bem nos nossos olhos e diz:\n\"Coragem! Para de olhar para as circunstâncias!\"\nDe repente, sobre as águas, aparece Jesus e olha nos seus olhos.\nE ele diz:\n\"Coragem. Para de olhar para as circunstâncias. Olhe para aquilo que Eu posso fazer.\"\nExiste algo que o Mestre não pode fazer?\nMateus 14:28-33\nTemos dois pontos interessantes.\nTemos Pedro um exemplo de fé.\nTemos doze homens dentro do barco e apenas um deles se moveu em direção ao Mestre.\nPedro deu um passo que ninguém deu.\nPrecisamos aprender com Pedro. Se Jesus mandou sair, nós devemos dar os primeiros passos.\nNaquele momento, não podemos minimizar o que Pedro fez.\nExistem momentos, que Jesus nos dá direcionamentos que parecem impossíveis.\nSe foi Jesus quem falou, vai em frente.\nPorque é Ele quem constrói o caminho seguro.\nFoi assim com Abraão. Abraão só tinha a voz de Deus, mas se Deus mandou, ele foi.\nTemos Pedro também,  o exemplo de incredulidade.\nUm homem que dá um passo que ninguém dá. Que vê o que ninguém vê.\nMas de repente, enquanto caminha naquilo que Jesus direcionou, o medo toma conta do seu coração. Pedro deixa de olhar para o Mestre e começa a olhar ao redor.\nPedro deixa de olhar para Aquele que o conduziria em segurança.\nMas de repente, o Senhor nos ensina, que aquilo que Pedro vive em poucos segundos, diz muito das nuances do coração do homem.\nO texto nos diz que o vento toca Pedro. Pedro sente o vento. Pedro olha para a impossibilidade que ele está vivendo. Ele começa a afundar, porque ele tira os olhos do Mestre e começa a olhar para as circunstâncias que o acometem.\nTalvez, o Senhor Jesus está desafiando você.\n\"Continue a olhar para Mim. Continue a ouvir a Minha voz.\"\nPorque quando olhamos para Jesus e ouvimos a Sua voz, não damos espaço para as tempestades ao redor.\nEsse é o Jesus que nos chama para viver o extraordinário.\nE  mesmo que hoje, ao segui-Lo, você esteja numa tempestade, mas, existe algo que ninguém tirará de você. Porque agora, você é comprado pelo Sangue do Cordeiro, é um filho de Deus\nA certeza daquele que crê em Jesus, independente daquilo que ocorra, estou seguro se olho para o Mestre.\nEstevão não é livrado por Deus da tempestade que o acometia. Mas enquanto morria apedrejado, Estevão estava com os olhos fitos em Jesus.\nMateus 14:33\nO Senhor Jesus que se apresenta a cada um de nós, é Aquele que faz coisas extraordinárias.\nMas só colhemos coisas extraordinárias com Deus, quando reconhecemos verdadeiramente, quem Ele é.\nTendo seus rostos cansados, eles caminham, porque sabem que uma Pátria melhor os aguarda.\nO que Deus fez na sua vida?\nNunca se esqueça daquilo que Deus fez e daquilo que Deus está fazendo.\nAqueles discípulos viveram grandes milagres. Mas no momento em que sua fé foi provada, a humanidade gritou em seu coração.\nEstamos entrando em um novo ano. Você tem a oportunidade de fixar seu olhar em algum lugar.\nMas o chamado do Mestre é:\n\"Olha para Mim.\"\nAs tempestades da vida virão. E aqueles que estiverem com seus olhos fitos em Jesus, passarão por elas, vitoriosos, porque reconhecem quem verdadeiramente é o nosso Deus.\nGuarde isso no seu coração:\n\"A diferença entre o pânico e a coragem, não é a ausência de ondas. Mas é a  direção do seu olhar.\"\nSe você fixar os olhos no Mestre, poderá andar, enquanto o mundo grita.\nPastor Gabriel Monteiro\nIBPS",
      "conteudo_limpo": "11/01/2026\n\" Ano Novo - Olhe para o Mestre \"\nGuarde isso no seu coração:\n\"Quando estamos próximos de Jesus as impossibilidades se tornam possibilidades. Porque nada é impossível para Aquele que criou todas as coisas.\"\nMateus 14:22-27\nAo olhar para esse texto, a primeira pergunta a nos fazer é:\nPor que Jesus não acompanha os seus discípulos?\nPor que Jesus, de repente, precisa ficar só?\nO próprio texto nos informa essa resposta.\nPorque Jesus precisava de orar.\nPorque Jesus precisava de tempo a sós com o Pai. Porque Jesus precisava regar o relacionamento com o Pai.\nMesmo sendo Deus encarnado.\nMesmo sendo Aquele que criou todas as coisas.\nNo estado de humilhação, isto é, em que Cristo Jesus se torna homem, Ele nos ensina a importância da comunhão com o Pai.\nOração não é um capricho religioso.\nA oração deve ser um movimento de um coração que compreende, que as impossibilidades das nossas mãos, são possibilidades nas mãos de Deus.\nA oração coloca os joelhos dos homens, que muitas vezes se acham verdadeiros deuses, dobrados em humilhação, sobre o reconhecimento de quem Deus é.\nO crente que não ora, é o crente que não aprendeu a se deleitar na presença de Deus.\nMuitas vezes, a oração começa como uma disciplina, mas ela tem que se  transformar, em prazer, de estar em comunhão com Aquele, que pode o que não podemos.\nAqueles que não amam a presença de Deus nessa terra, o que querem fazer no céu?\nA oração é fundamental para manter-nos, de pé.\nSe o Próprio Cristo precisava de oração e de um tempo a sós com o Pai, quem dirá nós?!\nJESUS retirava-se das multidões.\nJesus direcionava-se a um lugar só.\nPorque a oração, deve ser algo que nos leva, completamente entregues à presença de um Deus, que não apenas escuta o que precisamos, mas que devemos entrar, em espírito de adoração e sede, pela presença do grande EU SOU.\nMateus 6:6\nComo será sua vida de oração, em 2026?\nOlhe para Jesus e você viverá tempos extraordinários, diante de Deus.\nO texto nos aponta para o movimento de Jesus ao encontro daqueles homens.\nEle termina de orar e de repente, Ele vai ao encontro daqueles que O esperam.\nA situação daqueles discípulos, que aguardam o Mestre, é complicada.\nUma tempestade se estabelece sobre a vida daqueles que seguem a Jesus.\nO barco está sendo levado de um lado para o outro.\nImagine o que se passava no coração daqueles homens, que deixaram o Mestre para trás!\nA tempestade recai sobre a vida dos seguidores de Jesus.\nCaminhar com Jesus não significa viver em meio ao mar tranquilo.\nCaminhar com Jesus não significa que as ondas deixarão de bater na sua casa.\nCaminhar com Jesus, não significa que você será livrado de todas as provações dessa terra.\nCristo não nos promete águas tranquilas.\nA vida, por muitos momentos,  nos sacode de um lado para o outro.\nExistem momentos, que seremos nós, dentro do barco.\nMas existe algo, que não pode sair do coração daquele que crê - que Jesus está vindo ao seu encontro.\nAqueles discípulos estão em meio a tempestade, mas Jesus está vindo ao seu encontro.\nAs tempestades da vida tendem, em muitos momentos, nos fazer  esquecer que Jesus está vindo ao nosso encontro.\nNão desista!\nAqueles que temem a Jesus, de maneira nenhuma serão desamparados.\nO texto nos diz que era alta madrugada. Estamos em um momento em que a tempestade se inside.\nA quarta vigília da noite, é o momento mais escuro da madrugada.\nNaquele momento não há mais recurso marítimo.\nA desesperança começa a bater à porta.\n\"O que será de nós, que estamos aqui nesse mar?\"\n\"Será que Jesus nos tirou daquele lugar de rotina, para nos trazer ao mar revolto e tirar a nossa vida?\"\nO que se passa no seu coração, nos momentos de dor?\nDeus não se esqueceu de você!\nDeus não está indiferente a sua dor!\nPor muitos momentos, a caminhada do Mestre até você, demora um tempo. Ele está ensinando você, sobre ter fé. Sobre perseverar em meio às provações.\nAs tempestades da vida, nem sempre vem para destruir a sua história.\nMuitas vezes, elas vêm, para afiar o seu coração, transbordar a graça de Deus  e te fazer mais parecido com Jesus.\nNaquele momento, na alta madrugada - \"De onde me virá o socorro?\"\nEis que vem uma figura distante.\n\" É um fantasma! \"\nGritam com muito medo.\nNa cultura judaica, acreditava-se que onde as pessoas morriam, a alma ficava por algum tempo ali.\n\"Estamos vendo uma assombração?\"\nJesus vem andando sobre as águas.\nA fala de Jesus para aqueles homens é a mesma para cada um de nós.\n\"Coragem! Sou Eu. Não tenham medo.\"\nEssa é a voz do Senhor para conosco.\nExistem momentos que precisamos abrir nossos ouvidos, em meio ao caos, para ouvir Jesus dizendo:\n\"Coragem!\"\nNesse momento, a tempestade não cessa. A calmaria não vem.\nEm meio aquele caos, Jesus os convida a olhar para Ele.\nE Ele diz:\n\"Coragem! Sou Eu. Não tenham medo.\"\nA calmaria não ocorre de imediato. Mas isso não importava mais.\nSó compreendemos momentos como esses, quando estamos imersos nas tempestades da vida.\nQuando não encontramos solução, de repente se apresenta, Cristo Jesus, andando sobre as águas. E Ele olha bem nos nossos olhos e diz:\n\"Coragem! Para de olhar para as circunstâncias!\"\nDe repente, sobre as águas, aparece Jesus e olha nos seus olhos.\nE ele diz:\n\"Coragem. Para de olhar para as circunstâncias. Olhe para aquilo que Eu posso fazer.\"\nExiste algo que o Mestre não pode fazer?\nMateus 14:28-33\nTemos dois pontos interessantes.\nTemos Pedro um exemplo de fé.\nTemos doze homens dentro do barco e apenas um deles se moveu em direção ao Mestre.\nPedro deu um passo que ninguém deu.\nPrecisamos aprender com Pedro. Se Jesus mandou sair, nós devemos dar os primeiros passos.\nNaquele momento, não podemos minimizar o que Pedro fez.\nExistem momentos, que Jesus nos dá direcionamentos que parecem impossíveis.\nSe foi Jesus quem falou, vai em frente.\nPorque é Ele quem constrói o caminho seguro.\nFoi assim com Abraão. Abraão só tinha a voz de Deus, mas se Deus mandou, ele foi.\nTemos Pedro também,  o exemplo de incredulidade.\nUm homem que dá um passo que ninguém dá. Que vê o que ninguém vê.\nMas de repente, enquanto caminha naquilo que Jesus direcionou, o medo toma conta do seu coração. Pedro deixa de olhar para o Mestre e começa a olhar ao redor.\nPedro deixa de olhar para Aquele que o conduziria em segurança.\nMas de repente, o Senhor nos ensina, que aquilo que Pedro vive em poucos segundos, diz muito das nuances do coração do homem.\nO texto nos diz que o vento toca Pedro. Pedro sente o vento. Pedro olha para a impossibilidade que ele está vivendo. Ele começa a afundar, porque ele tira os olhos do Mestre e começa a olhar para as circunstâncias que o acometem.\nTalvez, o Senhor Jesus está desafiando você.\n\"Continue a olhar para Mim. Continue a ouvir a Minha voz.\"\nPorque quando olhamos para Jesus e ouvimos a Sua voz, não damos espaço para as tempestades ao redor.\nEsse é o Jesus que nos chama para viver o extraordinário.\nE  mesmo que hoje, ao segui-Lo, você esteja numa tempestade, mas, existe algo que ninguém tirará de você. Porque agora, você é comprado pelo Sangue do Cordeiro, é um filho de Deus\nA certeza daquele que crê em Jesus, independente daquilo que ocorra, estou seguro se olho para o Mestre.\nEstevão não é livrado por Deus da tempestade que o acometia. Mas enquanto morria apedrejado, Estevão estava com os olhos fitos em Jesus.\nMateus 14:33\nO Senhor Jesus que se apresenta a cada um de nós, é Aquele que faz coisas extraordinárias.\nMas só colhemos coisas extraordinárias com Deus, quando reconhecemos verdadeiramente, quem Ele é.\nTendo seus rostos cansados, eles caminham, porque sabem que uma Pátria melhor os aguarda.\nO que Deus fez na sua vida?\nNunca se esqueça daquilo que Deus fez e daquilo que Deus está fazendo.\nAqueles discípulos viveram grandes milagres. Mas no momento em que sua fé foi provada, a humanidade gritou em seu coração.\nEstamos entrando em um novo ano. Você tem a oportunidade de fixar seu olhar em algum lugar.\nMas o chamado do Mestre é:\n\"Olha para Mim.\"\nAs tempestades da vida virão. E aqueles que estiverem com seus olhos fitos em Jesus, passarão por elas, vitoriosos, porque reconhecem quem verdadeiramente é o nosso Deus.\nGuarde isso no seu coração:\n\"A diferença entre o pânico e a coragem, não é a ausência de ondas. Mas é a  direção do seu olhar.\"\nSe você fixar os olhos no Mestre, poderá andar, enquanto o mundo grita.\nPastor Gabriel Monteiro\nIBPS",
      "tamanho_texto": 8358,
      "url_blog": "https://pregacoesibps.blogspot.com/2026/01/ano-novo-olhe-para-o-mestre.html",
      "url_youtube": "",
      "tags": [],
      "_metadados": {
        "ano_arquivo": 2026,
        "igreja": "",
        "processado_em": "2026-01-16T13:57:17.383370",
        "data_fonte": "texto"
      },
      "id_unico": "2026_001",
      "metadados_biblicos": {
        "livro_principal": "Mateus",
        "texto_base": null,
        "total_referencias": 4,
        "referencias_titulo": 0,
        "referencias_conteudo": 4,
        "livros_mencionados": [
          "Mateus"
        ],
        "todas_referencias": [
          "Mateus 14:22-27",
          "Mateus 6:6",
          "Mateus 14:28-33",
          "Mateus 14:33"
        ]
      }
    },
    {
      "id_original": 2,
      "titulo": "Ano Novo - Relacionamentos restaurados",
      "data_pregacao": "11/01/2026",
      "ano": 2026,
      "pregador": "Gabriel Monteiro",
      "tipo_pregador": "oficial",
      "conteudo_original": "Resenha do Culto da manhã de Domingo\n11/01/2026\n\"Ano Novo - Relacionamentos restaurados\"\nMateus 18:21-22\nO Senhor Jesus está ensinando os discípulos a tratar das disciplinas eclesiásticas.\nDe forma interessante, Pedro se aproxima de Jesus. E pergunta:\nE se o irmão cometer algo contra mim.\nO contexto é o perdão.\nMateus 18:21\nAgora estamos falando de uma ofensa pessoal. De algo que afeta o nosso relacionamento. Estamos falando de uma ação que trouxe sofrimento. Que trouxe uma divisão.\n\"Mestre, até quantas vezes deverei perdoar o meu irmão que me feriu? Até sete vezes?\"\nNão é à toa que Pedro pergunta:\n\"até sete vezes!\"\nO número sete, na cultura judaica tem um significado muito especial - significa completude, totalidade.\nQuando Pedro faz essa pergunta, é como se ele estivesse colocando uma quantidade de vezes exagerada. Que quase ninguém está disposto a fazer.\nPorque se a lógica do mundo é não perdoar ou perdoar apenas uma vez, qual seria a lógica do Reino de Deus?\nAté sete?\nNeste momento temos a resposta de Jesus, que transmite uma profundidade tremenda para nós.\nEm algum momento da vida, você já foi ferido por alguém.\nJesus olha para Pedro e expõe a lógica do Reino de Deus.\nMateus 18:22\nA ideia de Jesus é transmitir, que liberar perdão, faz parte do DNA de quem caminha com Ele.\nPor mais difícil que seja, é o caminho natural para quem é filho de Deus.\nMateus 18:23-24\nO talento era a maior unidade monetária. Um talento equivalia a vinte anos de salário diário de um trabalhador. Estamos falando de uma dívida astronômica. Uma dívida impagável.\nMateus 18:25-28\nCem denários representava quatro meses de trabalho.\nUma dívida pagável.\nMateus 18:29-35\nEssa parábola contada por Jesus reflete a relação de Deus com o homem e dos homens com os homens.\nA relação de Deus com os homens é a relação daquele servo que deve dez mil talentos ao seu Senhor.\nÉ impagável.\nNinguém te ofenderá quanto você ofendeu ao Deus Todo Poderoso.\nNinguém deverá, tanto a você, quanto você um dia deveu, ao Deus Todo Poderoso.\nMas um dia, o toque da Graça Daquele a quem somos devedores, veio sobre nós.\nCheio de misericórdia e amor, diante da nossa confissão e arrependimento, Ele decidiu perdoar-nos.\nEle decidiu tratar-nos como filhos e não como devedores.\nÉ Deus perdoando você, que devia dez mil talentos. Que não poderia pagar tão grande ofensa.\nA grande pergunta é:\nContinuará você a não perdoar, aquele que te deve cem denários?\nO que fizeram contra você?\nTe magoaram com palavras?\nTe deram um tombo financeiro?\nTraíram a sua confiança? Falaram mal de você?\nO que fizeram contra você?\nAquele que retém o perdão, é o maior prejudicado.\nCarregar amargura te torna uma pessoa amarga, triste, solitária, insegura.\nO cristão não deve alimentar o sentimento mal. Mesmo quando não há arrependimento daquele que te machucou.\nSomos chamados a viver uma lógica contrária a deste século.\nO perdão deve ser algo natural ao crente. Faz parte de quem somos.\nReter o perdão, é construir um poço de amargura dentro do coração.\nTalvez, a pessoa que te ofendeu não está nem lembrando disso!\nExistem pessoas que não se arrependerão dos seus erros. Pessoas tomadas pelo orgulho, pela vaidade, que não reconhecerão as suas faltas. E isso é problema delas com Deus.\nNão é sobre se tornar novamente o melhor amigo, ou reatar o relacionamento fracassado.\nÉ sobre ter a oportunidade de ministrar sobre o outro, a graça que um dia foi ministrada sobre você.\nEm meio às provas da vida, é que o nosso caráter é formado.\nComo saberíamos o que é perdoar, se nunca fôssemos ofendidos?\nComo saberíamos o que é amar, se em algum momento, não tivéssemos que passar por cima de questões que nos machucam?\nComo saberíamos  o que é a Graça de Deus, se um dia não vivêssemos situações que nos fariam ter que agir com graça?\nGraça sou eu, perdoando aquele que não merece perdão.\nNão é isso que o Senhor Deus fez, com cada um de nós?\nBasta olhar para Jesus!\nEle está na cruz do calvário, crucificado, sendo zombado, humilhado, e Ele olha para o céu e fala:\n\" Pai, perdoa porque eles não sabem o que fazem.\"\nVocê quer maior exemplo disso?\nMuitas vezes, estamos amargurados, com pessoas que são nossos irmãos na fé. Pessoas que estão ao nosso redor.\nReter perdão prejudica a própria pessoa.\nPerdoar é muitas vezes sofrer o dano. É transferir o dano diante da cruz de Cristo, para que Ele possa apaziguar o sofrimento do nosso coração.\nMateus 6:12\nAlgo que deveria ser natural na oração. Porque você será ferido por alguém, enquanto você viver.\nComo povo de Deus, precisamos compreender, que o perdão faz parte do nosso DNA.\nMateus 6:14-15\nEsse texto é muito claro. Perdoa para ser perdoado.\nVocê quer o perdão de  Deus em dez mil talentos, mas não quer perdoar o irmão que te deve cem?\nO perdão é uma atitude que fortalece a nossa fé.\nDependendo da ofensa que recebemos, realmente dói. Mas precisamos entender que precisamos chegar ao momento do perdão.\nO perdão não está apenas protegendo a sua honra e afiando a sua fé. Ele está também protegendo a sua saúde.\nPerdoar é uma prescrição do Médico dos médicos.\nO perdão desbloqueia a sua intimidade com Deus.\nQuando você perdoa, há uma quebra geracional.\nO perdão fortalece as nossas virtudes.\nQuando perdoamos conseguimos compreender melhor o que é a Graça de Deus e nos identificar melhor com este Deus da Graça.\nMateus 18:34\nO texto inicia com o Senhor perdoando uma dívida impagável.\nE finaliza com o senhor colocando aquele servo mau na prisão, até que ele pague uma dívida.\nQuando ele vai pagar?\nNunca!\nUma dívida impagável, de alguém que está preso e não pode trabalhar.\nO chamado do Senhor para sua vida, é que você possa trazer á memória aquilo que você precisa liberar perdão.\nEstamos iniciando um novo ano, deixe as mágoas e as marcas do ano passado, para trás.\nDeixe as marcas do seu passado para trás.\nSomos convidados a retirar esse fardo.\nPense nesse dia:\n\" A quem você precisa perdoar?\"\nA pergunta NÃO é :\n\" Essa pessoa merece perdão?\"\nA pergunta é:\n\" Você que foi perdoado, por que ainda não perdoou?\"\nPorque de merecimento por merecimento, ninguém merece.\nAno Novo - deixemos as mágoas antigas para trás.\nÉ tempo de viver o novo de Deus  para a sua vida.\nAs vezes, você tem que perdoar alguém.\nMas as vezes, você tem que perdoar a si mesmo.\n\"Não perdoar é tomar, o veneno para o rato, esperando que o rato morra.\"\nOs efeitos não ocorrerão em relação a pessoa que te ofendeu. Mas serão devastadores na sua alma, no seu coração.\nPastor Gabriel Monteiro\nIBPS",
      "conteudo_limpo": "11/01/2026\n\"Ano Novo - Relacionamentos restaurados\"\nMateus 18:21-22\nO Senhor Jesus está ensinando os discípulos a tratar das disciplinas eclesiásticas.\nDe forma interessante, Pedro se aproxima de Jesus. E pergunta:\nE se o irmão cometer algo contra mim.\nO contexto é o perdão.\nMateus 18:21\nAgora estamos falando de uma ofensa pessoal. De algo que afeta o nosso relacionamento. Estamos falando de uma ação que trouxe sofrimento. Que trouxe uma divisão.\n\"Mestre, até quantas vezes deverei perdoar o meu irmão que me feriu? Até sete vezes?\"\nNão é à toa que Pedro pergunta:\n\"até sete vezes!\"\nO número sete, na cultura judaica tem um significado muito especial - significa completude, totalidade.\nQuando Pedro faz essa pergunta, é como se ele estivesse colocando uma quantidade de vezes exagerada. Que quase ninguém está disposto a fazer.\nPorque se a lógica do mundo é não perdoar ou perdoar apenas uma vez, qual seria a lógica do Reino de Deus?\nAté sete?\nNeste momento temos a resposta de Jesus, que transmite uma profundidade tremenda para nós.\nEm algum momento da vida, você já foi ferido por alguém.\nJesus olha para Pedro e expõe a lógica do Reino de Deus.\nMateus 18:22\nA ideia de Jesus é transmitir, que liberar perdão, faz parte do DNA de quem caminha com Ele.\nPor mais difícil que seja, é o caminho natural para quem é filho de Deus.\nMateus 18:23-24\nO talento era a maior unidade monetária. Um talento equivalia a vinte anos de salário diário de um trabalhador. Estamos falando de uma dívida astronômica. Uma dívida impagável.\nMateus 18:25-28\nCem denários representava quatro meses de trabalho.\nUma dívida pagável.\nMateus 18:29-35\nEssa parábola contada por Jesus reflete a relação de Deus com o homem e dos homens com os homens.\nA relação de Deus com os homens é a relação daquele servo que deve dez mil talentos ao seu Senhor.\nÉ impagável.\nNinguém te ofenderá quanto você ofendeu ao Deus Todo Poderoso.\nNinguém deverá, tanto a você, quanto você um dia deveu, ao Deus Todo Poderoso.\nMas um dia, o toque da Graça Daquele a quem somos devedores, veio sobre nós.\nCheio de misericórdia e amor, diante da nossa confissão e arrependimento, Ele decidiu perdoar-nos.\nEle decidiu tratar-nos como filhos e não como devedores.\nÉ Deus perdoando você, que devia dez mil talentos. Que não poderia pagar tão grande ofensa.\nA grande pergunta é:\nContinuará você a não perdoar, aquele que te deve cem denários?\nO que fizeram contra você?\nTe magoaram com palavras?\nTe deram um tombo financeiro?\nTraíram a sua confiança? Falaram mal de você?\nO que fizeram contra você?\nAquele que retém o perdão, é o maior prejudicado.\nCarregar amargura te torna uma pessoa amarga, triste, solitária, insegura.\nO cristão não deve alimentar o sentimento mal. Mesmo quando não há arrependimento daquele que te machucou.\nSomos chamados a viver uma lógica contrária a deste século.\nO perdão deve ser algo natural ao crente. Faz parte de quem somos.\nReter o perdão, é construir um poço de amargura dentro do coração.\nTalvez, a pessoa que te ofendeu não está nem lembrando disso!\nExistem pessoas que não se arrependerão dos seus erros. Pessoas tomadas pelo orgulho, pela vaidade, que não reconhecerão as suas faltas. E isso é problema delas com Deus.\nNão é sobre se tornar novamente o melhor amigo, ou reatar o relacionamento fracassado.\nÉ sobre ter a oportunidade de ministrar sobre o outro, a graça que um dia foi ministrada sobre você.\nEm meio às provas da vida, é que o nosso caráter é formado.\nComo saberíamos o que é perdoar, se nunca fôssemos ofendidos?\nComo saberíamos o que é amar, se em algum momento, não tivéssemos que passar por cima de questões que nos machucam?\nComo saberíamos  o que é a Graça de Deus, se um dia não vivêssemos situações que nos fariam ter que agir com graça?\nGraça sou eu, perdoando aquele que não merece perdão.\nNão é isso que o Senhor Deus fez, com cada um de nós?\nBasta olhar para Jesus!\nEle está na cruz do calvário, crucificado, sendo zombado, humilhado, e Ele olha para o céu e fala:\n\" Pai, perdoa porque eles não sabem o que fazem.\"\nVocê quer maior exemplo disso?\nMuitas vezes, estamos amargurados, com pessoas que são nossos irmãos na fé. Pessoas que estão ao nosso redor.\nReter perdão prejudica a própria pessoa.\nPerdoar é muitas vezes sofrer o dano. É transferir o dano diante da cruz de Cristo, para que Ele possa apaziguar o sofrimento do nosso coração.\nMateus 6:12\nAlgo que deveria ser natural na oração. Porque você será ferido por alguém, enquanto você viver.\nComo povo de Deus, precisamos compreender, que o perdão faz parte do nosso DNA.\nMateus 6:14-15\nEsse texto é muito claro. Perdoa para ser perdoado.\nVocê quer o perdão de  Deus em dez mil talentos, mas não quer perdoar o irmão que te deve cem?\nO perdão é uma atitude que fortalece a nossa fé.\nDependendo da ofensa que recebemos, realmente dói. Mas precisamos entender que precisamos chegar ao momento do perdão.\nO perdão não está apenas protegendo a sua honra e afiando a sua fé. Ele está também protegendo a sua saúde.\nPerdoar é uma prescrição do Médico dos médicos.\nO perdão desbloqueia a sua intimidade com Deus.\nQuando você perdoa, há uma quebra geracional.\nO perdão fortalece as nossas virtudes.\nQuando perdoamos conseguimos compreender melhor o que é a Graça de Deus e nos identificar melhor com este Deus da Graça.\nMateus 18:34\nO texto inicia com o Senhor perdoando uma dívida impagável.\nE finaliza com o senhor colocando aquele servo mau na prisão, até que ele pague uma dívida.\nQuando ele vai pagar?\nNunca!\nUma dívida impagável, de alguém que está preso e não pode trabalhar.\nO chamado do Senhor para sua vida, é que você possa trazer á memória aquilo que você precisa liberar perdão.\nEstamos iniciando um novo ano, deixe as mágoas e as marcas do ano passado, para trás.\nDeixe as marcas do seu passado para trás.\nSomos convidados a retirar esse fardo.\nPense nesse dia:\n\" A quem você precisa perdoar?\"\nA pergunta NÃO é :\n\" Essa pessoa merece perdão?\"\nA pergunta é:\n\" Você que foi perdoado, por que ainda não perdoou?\"\nPorque de merecimento por merecimento, ninguém merece.\nAno Novo - deixemos as mágoas antigas para trás.\nÉ tempo de viver o novo de Deus  para a sua vida.\nAs vezes, você tem que perdoar alguém.\nMas as vezes, você tem que perdoar a si mesmo.\n\"Não perdoar é tomar, o veneno para o rato, esperando que o rato morra.\"\nOs efeitos não ocorrerão em relação a pessoa que te ofendeu. Mas serão devastadores na sua alma, no seu coração.\nPastor Gabriel Monteiro\nIBPS",
      "tamanho_texto": 6482,
      "url_blog": "https://pregacoesibps.blogspot.com/2026/01/ano-novo-relacionamentos-restaurados.html",
      "url_youtube": "",
      "tags": [],
      "_metadados": {
        "ano_arquivo": 2026,
        "igreja": "",
        "processado_em": "2026-01-16T13:57:17.383889",
        "data_fonte": "texto"
      },
      "id_unico": "2026_002",
      "metadados_biblicos": {
        "livro_principal": "Mateus",
        "texto_base": null,
        "total_referencias": 9,
        "referencias_titulo": 0,
        "referencias_conteudo": 9,
        "livros_mencionados": [
          "Mateus"
        ],
        "todas_referencias": [
          "Mateus 18:21-22",
          "Mateus 18:21",
          "Mateus 18:22",
          "Mateus 18:23-24",
          "Mateus 18:25-28",
          "Mateus 18:29-35",
          "Mateus 6:12",
          "Mateus 6:14-15",
          "Mateus 18:34"
        ]
      }
    },
    {
      "id_original": 3,
      "titulo": "Ano Novo - É necessário abandonar",
      "data_pregacao": "04/01/2026",
      "ano": 2026,
      "pregador": "Gabriel Monteiro",
      "tipo_pregador": "oficial",
      "conteudo_original": "Resenha do Culto da noite de Domingo\n04/01/2026\n\"Ano Novo - É necessário abandonar \"\nMateus 19:16-22\nEsse texto não diz apenas de um momento singular de um homem com Jesus. Ele diz dos encontros diários que nós também,  temos com Cristo.\nAlgo motivou o coração daquele jovem a ir até Jesus.\nTalvez, o ouvir das multidões que O seguiam.\nTalvez, a percepção de que Aquele a quem muitas pessoas davam ouvidos, fazia coisas extraordinárias, muitos milagres.\nAlgo toca no coração desse jovem, que o impulsiona a sair do seu lugar de conforto e enfrentar as multidões que seguiam a Cristo e se encontrar com Jesus.\nO que te impulsionou a estar aqui, nesta noite?\nAlguma coisa te motivou a estar aqui nesta noite, assim como motivou aquele homem, a ir diante de Jesus.\nAssim como aquele jovem, você está aqui!\nAquele jovem, se encontra diante de Jesus e na oportunidade, traz uma pergunta que incomodava o seu coração.\n\" Mestre, o que devo fazer de bom, para herdar a vida eterna?\"\nEu incentivo você a levar as suas questões diante de Deus.\nDiante da oportunidade dada, aquele jovem, faz a Jesus, a pergunta que incomodava seu coração.\n\"O que farei de bom para herdar a vida eterna?\"\nO que é a vida eterna?\nAo longo dos Evangelhos, percebemos Jesus falar sobre esse tipo de vida. Ess tipo de vida que não termina.\nEsse tipo de vida, reservado, para aqueles que creram no Nome do Filho Unigênito de Deus.\nUm tipo de vida reservado, em um futuro que está por vir, onde cada um de nós, um dia, estaremos diante do tribunal de Deus, mas, que aqueles que depositaram a sua fé em Jesus, receberão por herança, um Reino que não tem fim. Onde não há dor. Onde o pecado não tem mais domínio sobre nosso corpo.\nAquele jovem tem o desejo que é o desejo das nossas almas.\nO que fazer para herdar a vida eterna?\nO que você perguntaria para Jesus, se tivesse uma oportunidade?\nExiste uma preocupação natural aqui.\nSerá que a minha vida, se demonstra digna das bênçãos do porvir?\nO que me falta para herdar a vida?\nTe falta algo?\nSerá que você é digno desta grande benção?\nA resposta de Jesus tem como alvo, não nos ensinar que é possível pelas nossas mãos alcançar essa nova vida.\nMas, Jesus prepara o caminho, para tratar o coração daquele jovem.\nA resposta do Mestre tem como levá-lo a uma reflexão, assim como Ele faz diversas vezes, com cada um de nós.\nO Senhor diz:\n\"Guarde os mandamentos.\"\nEssa é a resposta.\nO Senhor Jesus aponta para aquele jovem, aqueles mandamentos que refletem uma vida de integridade.\nE a resposta daquele jovem é:\n\" Mestre, eu os tenho guardado desde a minha mocidade.\"\nA resposta daquele jovem, nos faz compreender o tipo de vida que se espera de nós. Daqueles que guardam os mandamentos.\nMas, estamos diante Daquele, que sonda o mais íntimo do nosso ser.\nO bom testemunho público, diz da forma como as pessoas enxergam a nossa vida.\nMas existe Aquele que vê o que as pessoas não estão vendo. Aquele que vê a alma. E diante desse Deus, não se pode nada esconder.\nSalmos 139:7-12\nO que Davi, inspirado por Deus está dizendo?\nNão existe lugar nenhum no mundo, que possamos nos esconder da face de Deus.\nEle conhece todas as coisas. Ele sonda o mais íntimo dos seus pensamentos.\nNão existe nada oculto, diante dos olhos Daquele que conhece todas as coisas.\nDessa forma, o diagnóstico Divino apontou para a necessidade de abandonar.\nPorque as riquezas, em si mesmas, não são maléficas. Muitos casos carregam consigo, o potencial de se tornarem verdadeiros ídolos no coração dos homens.\nA Bíblia fala mais do problema do dinheiro, do que da grande maioria, dos outros problemas, enfrentados pelo homem.\nIsso não significa que ter recursos é pecado.\nSignifica que existe uma grande inclinação no coração dos homens, em colocar a confiança do seu coração, nas riquezas e não em Deus.\nTemos aqui, um jovem que guardava os mandamentos, mas a sua fé não estava em Deus.\nTemos um jovem íntegro em seus testemunhos, mas havia uma distância, entre a imagem transmitida e a verdade em sua alma.\nPor que fazemos o que fazemos?\nPor que servimos?\nPor que vivemos da forma que vivemos?\nEste jovem tinha um problema de apego e para esse problema, a  necessidade do abandono.\nPois, apesar de guardar todos os mandamentos, faltava-lhe uma coisa - \"Amar a Deus, acima de todas as coisas.\"\nÉ perfeitamente possível amarmos o próximo e ainda assim, não amarmos a Deus.\nO diagnóstico do coração deste homem, traz algo muito específico.\nDeus diz:\n\"É tempo de abandonar. É tempo de abandonar tudo aquilo que te afasta da presença de Deus. É tempo de abandonar para começar um novo ano diferente.\"\nAquele jovem traz uma pergunta a Jesus e a resposta de Jesus confronta o mais íntimo de um coração idólatra.\nComo é difícil abandonar aquilo que nos dá esperança!\nE o que dá esperança àquele homem, não é Deus.\nAs respostas de Deus nem sempre serão confortáveis.\nMas sempre apontarão para um lugar seguro.\nMuitas vezes, confrontarão a nossa idolatria, os nossos ídolos. Mas nos apontarão um caminho de excelência. E vai nos levando a experimentar um lugar, depois da tempestade que fomos acometidos.\nQuando nossos pecados são colocados diante de nossos olhos, dói.\nMas o abandono restaura a alma.\nDepois do encontro, nós temos o convite.\nApesar de focarmos no abandono necessário, nos esquecemos que aqui há um convite. Que deve trazer alegria ao coração, nesse processo de abandono.\nJesus diz:\n\" Se queres ser perfeito, vá e vende, o que você tem. Dá aos pobres e depois vem e siga-me.\"\nAquele jovem, apesar da necessidade de deixar para trás as riquezas, Jesus faz um convite:\n\"Você vai deixar as riquezas dessa terra, mas você vai receber  um tesouro indescritível.\"\nO Deus que nos chama ao abandono, também é o Deus que supre todas as nossas necessidades.\nO Deus que te chama nessa noite a abandonar algo, a deixar para trás o que te afasta de Deus, é o mesmo Deus que te toma pela mão e te dá um novo tempo. Uma nova história.\n\" Vem caminhar comigo, porque eu farei novas, todas as coisas.\"\nSe a fala de Cristo, fosse a mesma a você, qual seria nessa noite, a sua posição?\nMateus 19:22\nGeralmente, aquilo que Deus nos manda abandonar, está muito ligado àquilo que toma o nosso coração.\nO problema não era o jovem ter muitas propriedades. O problema, é que era isso que dominava a sua vida.\nQual a sua resposta diante do chamado de Deus?\nEsse encontro deste jovem, representa também o nosso encontro.\nNessa noite, mais uma oportunidade dada por Deus, para que você acerte a sua vida.\nMais uma oportunidade dada, para que você comece o ano diferente.\nAté quando?\nNós não sabemos a partir daqui, sobre esse jovem. Mas sabemos, que apesar de uma vida aparentemente íntegra, o seu coração estava longe da vontade de Deus.\nAquele jovem não tinha o Senhor, como seu Deus.\nAquele jovem estava completamente distante da presença de Deus.\nEssa foi a decisão desse homem ao se encontrar com Jesus.\nQual a sua postura, diante das oportunidades que Cristo tem te dado, ao longo da vida?\nMateus 19:23-30\nO Senhor Jesus deu um ensino claro aos seus discípulos,  a partir desse cenário.\nEle diz:\n\" Dificilmente um rico entrará no Reino dos céus.\"\nA grande questão não é porque sua conta está recheada. A grande questão é que seu coração está entregue.\nO seu coração também pode estar entregue.\nPode estar entregue a sua família, aos seus negócios, aos seus planos.\nO seu coração pode estar em lugares, que dificilmente te levarão para a presença de Deus.\nQuem pode alcançar a vida eterna?\nA resposta de Jesus, tira de nós o protagonismo da vida.\n\"Aos homens é impossível.\"\nO céu é de gente que reconheceu estar em pecado e confiou com todas as suas forças, no mérito de Cristo Jesus.\nA salvação é entregue a pecadores confessos e arrependidos.\nO caminho do céu não está nas suas mãos, mas sempre esteve nas mãos de Cristo.\nA fala de Jesus deve ecoar nos nossos corações.\nAo homem é impossível, mas a Deus, tudo é possível.\nDeus tem um chamado ao abandono em sua vida, nessa noite.\nVocê precisa deixar algo aos pés da cruz, para seguir a Cristo.\nEssa pode ser a noite crucial do seu encontro com Deus.\nEssa é a noite de colocar aos pés da cruz, tudo que tem te afastado dos seus santos e retos caminhos.\nVocê sabe e o Espírito de Deus sabe, o que precisa ser deixado para trás.\nPastor Gabriel Monteiro\nIBPS",
      "conteudo_limpo": "04/01/2026\n\"Ano Novo - É necessário abandonar \"\nMateus 19:16-22\nEsse texto não diz apenas de um momento singular de um homem com Jesus. Ele diz dos encontros diários que nós também,  temos com Cristo.\nAlgo motivou o coração daquele jovem a ir até Jesus.\nTalvez, o ouvir das multidões que O seguiam.\nTalvez, a percepção de que Aquele a quem muitas pessoas davam ouvidos, fazia coisas extraordinárias, muitos milagres.\nAlgo toca no coração desse jovem, que o impulsiona a sair do seu lugar de conforto e enfrentar as multidões que seguiam a Cristo e se encontrar com Jesus.\nO que te impulsionou a estar aqui, nesta noite?\nAlguma coisa te motivou a estar aqui nesta noite, assim como motivou aquele homem, a ir diante de Jesus.\nAssim como aquele jovem, você está aqui!\nAquele jovem, se encontra diante de Jesus e na oportunidade, traz uma pergunta que incomodava o seu coração.\n\" Mestre, o que devo fazer de bom, para herdar a vida eterna?\"\nEu incentivo você a levar as suas questões diante de Deus.\nDiante da oportunidade dada, aquele jovem, faz a Jesus, a pergunta que incomodava seu coração.\n\"O que farei de bom para herdar a vida eterna?\"\nO que é a vida eterna?\nAo longo dos Evangelhos, percebemos Jesus falar sobre esse tipo de vida. Ess tipo de vida que não termina.\nEsse tipo de vida, reservado, para aqueles que creram no Nome do Filho Unigênito de Deus.\nUm tipo de vida reservado, em um futuro que está por vir, onde cada um de nós, um dia, estaremos diante do tribunal de Deus, mas, que aqueles que depositaram a sua fé em Jesus, receberão por herança, um Reino que não tem fim. Onde não há dor. Onde o pecado não tem mais domínio sobre nosso corpo.\nAquele jovem tem o desejo que é o desejo das nossas almas.\nO que fazer para herdar a vida eterna?\nO que você perguntaria para Jesus, se tivesse uma oportunidade?\nExiste uma preocupação natural aqui.\nSerá que a minha vida, se demonstra digna das bênçãos do porvir?\nO que me falta para herdar a vida?\nTe falta algo?\nSerá que você é digno desta grande benção?\nA resposta de Jesus tem como alvo, não nos ensinar que é possível pelas nossas mãos alcançar essa nova vida.\nMas, Jesus prepara o caminho, para tratar o coração daquele jovem.\nA resposta do Mestre tem como levá-lo a uma reflexão, assim como Ele faz diversas vezes, com cada um de nós.\nO Senhor diz:\n\"Guarde os mandamentos.\"\nEssa é a resposta.\nO Senhor Jesus aponta para aquele jovem, aqueles mandamentos que refletem uma vida de integridade.\nE a resposta daquele jovem é:\n\" Mestre, eu os tenho guardado desde a minha mocidade.\"\nA resposta daquele jovem, nos faz compreender o tipo de vida que se espera de nós. Daqueles que guardam os mandamentos.\nMas, estamos diante Daquele, que sonda o mais íntimo do nosso ser.\nO bom testemunho público, diz da forma como as pessoas enxergam a nossa vida.\nMas existe Aquele que vê o que as pessoas não estão vendo. Aquele que vê a alma. E diante desse Deus, não se pode nada esconder.\nSalmos 139:7-12\nO que Davi, inspirado por Deus está dizendo?\nNão existe lugar nenhum no mundo, que possamos nos esconder da face de Deus.\nEle conhece todas as coisas. Ele sonda o mais íntimo dos seus pensamentos.\nNão existe nada oculto, diante dos olhos Daquele que conhece todas as coisas.\nDessa forma, o diagnóstico Divino apontou para a necessidade de abandonar.\nPorque as riquezas, em si mesmas, não são maléficas. Muitos casos carregam consigo, o potencial de se tornarem verdadeiros ídolos no coração dos homens.\nA Bíblia fala mais do problema do dinheiro, do que da grande maioria, dos outros problemas, enfrentados pelo homem.\nIsso não significa que ter recursos é pecado.\nSignifica que existe uma grande inclinação no coração dos homens, em colocar a confiança do seu coração, nas riquezas e não em Deus.\nTemos aqui, um jovem que guardava os mandamentos, mas a sua fé não estava em Deus.\nTemos um jovem íntegro em seus testemunhos, mas havia uma distância, entre a imagem transmitida e a verdade em sua alma.\nPor que fazemos o que fazemos?\nPor que servimos?\nPor que vivemos da forma que vivemos?\nEste jovem tinha um problema de apego e para esse problema, a  necessidade do abandono.\nPois, apesar de guardar todos os mandamentos, faltava-lhe uma coisa - \"Amar a Deus, acima de todas as coisas.\"\nÉ perfeitamente possível amarmos o próximo e ainda assim, não amarmos a Deus.\nO diagnóstico do coração deste homem, traz algo muito específico.\nDeus diz:\n\"É tempo de abandonar. É tempo de abandonar tudo aquilo que te afasta da presença de Deus. É tempo de abandonar para começar um novo ano diferente.\"\nAquele jovem traz uma pergunta a Jesus e a resposta de Jesus confronta o mais íntimo de um coração idólatra.\nComo é difícil abandonar aquilo que nos dá esperança!\nE o que dá esperança àquele homem, não é Deus.\nAs respostas de Deus nem sempre serão confortáveis.\nMas sempre apontarão para um lugar seguro.\nMuitas vezes, confrontarão a nossa idolatria, os nossos ídolos. Mas nos apontarão um caminho de excelência. E vai nos levando a experimentar um lugar, depois da tempestade que fomos acometidos.\nQuando nossos pecados são colocados diante de nossos olhos, dói.\nMas o abandono restaura a alma.\nDepois do encontro, nós temos o convite.\nApesar de focarmos no abandono necessário, nos esquecemos que aqui há um convite. Que deve trazer alegria ao coração, nesse processo de abandono.\nJesus diz:\n\" Se queres ser perfeito, vá e vende, o que você tem. Dá aos pobres e depois vem e siga-me.\"\nAquele jovem, apesar da necessidade de deixar para trás as riquezas, Jesus faz um convite:\n\"Você vai deixar as riquezas dessa terra, mas você vai receber  um tesouro indescritível.\"\nO Deus que nos chama ao abandono, também é o Deus que supre todas as nossas necessidades.\nO Deus que te chama nessa noite a abandonar algo, a deixar para trás o que te afasta de Deus, é o mesmo Deus que te toma pela mão e te dá um novo tempo. Uma nova história.\n\" Vem caminhar comigo, porque eu farei novas, todas as coisas.\"\nSe a fala de Cristo, fosse a mesma a você, qual seria nessa noite, a sua posição?\nMateus 19:22\nGeralmente, aquilo que Deus nos manda abandonar, está muito ligado àquilo que toma o nosso coração.\nO problema não era o jovem ter muitas propriedades. O problema, é que era isso que dominava a sua vida.\nQual a sua resposta diante do chamado de Deus?\nEsse encontro deste jovem, representa também o nosso encontro.\nNessa noite, mais uma oportunidade dada por Deus, para que você acerte a sua vida.\nMais uma oportunidade dada, para que você comece o ano diferente.\nAté quando?\nNós não sabemos a partir daqui, sobre esse jovem. Mas sabemos, que apesar de uma vida aparentemente íntegra, o seu coração estava longe da vontade de Deus.\nAquele jovem não tinha o Senhor, como seu Deus.\nAquele jovem estava completamente distante da presença de Deus.\nEssa foi a decisão desse homem ao se encontrar com Jesus.\nQual a sua postura, diante das oportunidades que Cristo tem te dado, ao longo da vida?\nMateus 19:23-30\nO Senhor Jesus deu um ensino claro aos seus discípulos,  a partir desse cenário.\nEle diz:\n\" Dificilmente um rico entrará no Reino dos céus.\"\nA grande questão não é porque sua conta está recheada. A grande questão é que seu coração está entregue.\nO seu coração também pode estar entregue.\nPode estar entregue a sua família, aos seus negócios, aos seus planos.\nO seu coração pode estar em lugares, que dificilmente te levarão para a presença de Deus.\nQuem pode alcançar a vida eterna?\nA resposta de Jesus, tira de nós o protagonismo da vida.\n\"Aos homens é impossível.\"\nO céu é de gente que reconheceu estar em pecado e confiou com todas as suas forças, no mérito de Cristo Jesus.\nA salvação é entregue a pecadores confessos e arrependidos.\nO caminho do céu não está nas suas mãos, mas sempre esteve nas mãos de Cristo.\nA fala de Jesus deve ecoar nos nossos corações.\nAo homem é impossível, mas a Deus, tudo é possível.\nDeus tem um chamado ao abandono em sua vida, nessa noite.\nVocê precisa deixar algo aos pés da cruz, para seguir a Cristo.\nEssa pode ser a noite crucial do seu encontro com Deus.\nEssa é a noite de colocar aos pés da cruz, tudo que tem te afastado dos seus santos e retos caminhos.\nVocê sabe e o Espírito de Deus sabe, o que precisa ser deixado para trás.\nPastor Gabriel Monteiro\nIBPS",
      "tamanho_texto": 8273,
      "url_blog": "https://pregacoesibps.blogspot.com/2026/01/ano-novo-e-necessario-abandonar.html",
      "url_youtube": "",
      "tags": [],
      "_metadados": {
        "ano_arquivo": 2026,
        "igreja": "",
        "processado_em": "2026-01-16T13:57:17.384515",
        "data_fonte": "texto"
      },
      "id_unico": "2026_003",
      "metadados_biblicos": {
        "livro_principal": "Mateus",
        "texto_base": null,
        "total_referencias": 4,
        "referencias_titulo": 0,
        "referencias_conteudo": 4,
        "livros_mencionados": [
          "Mateus",
          "Salmos"
        ],
        "todas_referencias": [
          "Mateus 19:16-22",
          "Salmos 139:7-12",
          "Mateus 19:22",
          "Mateus 19:23-30"
        ]
      }
    },
    {
      "id_original": 4,
      "titulo": "Ano Novo - Tempo de recomeçar. Mateus 11:28-30",
      "data_pregacao": "04/01/2026",
      "ano": 2026,
      "pregador": "Gabriel Monteiro",
      "tipo_pregador": "oficial",
      "conteudo_original": "Resenha do Culto da manhã de Domingo\n04/01/2026\n\"Ano Novo - Tempo de recomeçar \"\nMateus 11:28-30\nEis o contexto deste convite.\nO Senhor Jesus está falando dentro de uma realidade muito específica, mas que toca, o nosso tempo.\nEle está falando em um contexto, em que os religiosos daquele tempo, principalmente os fariseus, conhecedores da lei e rígidos no seu cumprimento e desdobramentos; e homens que colocavam fardos pesados, sobre os ombros de homens simples, trabalhadores. Homens decentes, mas que não conseguiriam cumprir tudo aquilo que a lei requeria. Religiosos que não conheciam de fato, a graça de Deus, mas colocavam peso extremo, que nem eles conseguiam cumprir, sobre a vida de homens e mulheres.\nQue ao olhar para a lei de Deus, se reconheciam como pecadores, como pequenos, como pessoas indignas.\nHomens que, ao olhar para as leis, perceberam quão estavam distantes daquilo que Deus espera.\nReconheceu algo que também precisamos - que Deus é Santo e nós somos pecadores!\nMas naquele contexto, o Senhor Jesus diz a esses homens:\n\" Eu espero dois movimentos de vocês. Porque eu tenho bênçãos. Eu tenho grandes coisas para fazer na vida de vocês.\"\nE o primeiro movimento de Jesus, Ele diz:\n\" Venham a mim!\"\nQuerido, o lugar do recomeço, é aos pés de Jesus.\nMuitas vezes estamos passando por dilemas, não sabemos por onde começar. Muitas vezes estamos passando por um caos familiar instaurado, já buscamos todo tipo de recursos, mas não viemos Àquele que pode resolver a nossa história!\nE o chamado de Jesus é para aqueles que estão cansados.\nTalvez você esteja cansado da lida da vida, das culpas, da amargura, da dificuldade de liberar perdão, do orgulho que corrói. Talvez você esteja cansado de cometer os mesmos pecados dia após dia. Talvez você esteja cansado de não conseguir sair desse lugar de maldição, que um dia você foi colocado.\nComo sair desse lugar e experimentar então, um recomeço?\nA resposta simples e clara do Evangelho - mergulhando na Graça de Deus.\nO chamado de Jesus é:\n\" Venha a mim \"\nEle não está dizendo:\nResolva as suas pendências, e depois venha a mim.\nEle está dizendo:\n\" Seja como for, seja como você estiver, com o fardo pesado na suas costas, venha a mim!\"\nVocê que se encontra inadequado, você que se encontra cheio de mágoas, você que se encontra cheio de culpas, você que se encontra cheio de pecados, você que já tentou de todas as formas, Ele diz:\n\" Se mova.\"\n\" Venha até mim para que eu mude a situação da sua história.\"\n\" Deixem que eu trabalhe em favor de vocês.\"\nIsaías 64:4\nO texto está falando que Deus trabalha, para aqueles que Nele esperam.\nÉ isso que Jesus Cristo está falando:\n\" Vinde a mim.\"\nVocê está cansado, porque você tenta do seu jeito.\nPara.\nNós somos filhos de Deus. Ele nos convoca a um relacionamento íntimo. A rasgar o coração. A se permitir ser tratado, ser cuidado. A saber que não é você que muda a sua história, mas é Deus, em Sua Graça e misericórdia.\nNós nos movemos, confiamos e esperamos, mas o trabalho é do Senhor.\nVocê está cansado, porque está trabalhando demais e confiando pouco.\nEsse é o problema.\nÉ exatamente isso que fazemos ao orar.\nA oração, é o homem inadequado, reconhecendo que precisa do mover de Deus na sua vida. É o reconhecimento de que se Deus não trabalhar ao nosso favor, em vão trabalharemos\nÀs vezes há o reconhecimento, mas não há o movimento.\nQual é o movimento?\n\"Venham a mim!\"\nSe permita ser tratado, se permita ser cuidado, se permita ser liberto.\nSalmos 50:15\nDeus e a pessoa que ora, são parceiros. Primeiro a sua parte - invocar o nome do Senhor. Depois, a parte de Deus - Eu o livrarei.\nNovamente a sua vez - receber essa graça. Depois, volta a vez para Deus - receber a Glória.\nAqui temos uma aliança, que Deus faz com você, enquanto você ora.\n\"Você terá o livramento e Eu terei a Glória.\"\n(Spurgeon)\nDeus é glorificado, enquanto trabalha em favor daqueles que O temem.\nEsse é o nosso Deus - Aquele que trabalha por aqueles que Nele esperam.\nPara recomeçar nesse novo ano, por que não vir até Jesus?\nExistem muitos crentes, que há anos estão tementes a Deus, mas que também estão precisando de um recomeço. Que se perderam no caminho, que sabemos que é longo.\nJesus está falando para você.\n\"Venha e encontre a transformação.\"\nA vida cristã não é uma corrida solo. É uma corrida acompanhada por Cristo.\nMateus 11:29\nExiste um segundo movimento - Tomar sobre si.\n\" Venha que Eu vou te dar o descanso.\"\nEle é um Deus que também nos chama a uma ação.\n\" Após eu fazer o extraordinário que você não consegue, existe uma ação que se espera de você.\nA fé cristã nos chama a um movimento.\n\" Eu vou tirar o jugo de vocês, para que você coloque o meu.\"\nComo é diferente o jugo de Jesus!\nÉ a plena confiança no Cristo Vivo.\nÉ um jugo onde somos imersos em meio a Graça e misericórdia.\nÉ um jugo onde somos ensinados a respeito daquele é Manso e Humilde de coração.\nColocar o fardo e o jugo de Jesus sobre nós, significa restaurar aquilo que nós somos e viver aquilo que nós fomos criados para viver.\nEle não retira o fardo e nos deixa inativos. Ele retira os fardos do pecado e coloca os seus.\nNo entanto, através da fé, nós percebemos como esses fardos são necessários para o nosso sustento.\nEm Cristo, nós encontramos o retirar do fardo, que aprisiona a alma. Nós encontramos o retirar da angústia, das mágoas, da culpa. Nós encontramos o retirar da dificuldade de perdoar. Nós retiramos o fardo da dificuldade de viver uma vida de integridade e encontramos então, um novo fardo. Mas um novo fardo, que nos faz ficar parecidos com Cristo dia após dia.\n\"Tome o meu jugo. Ele é suave, ele é leve. Aprendem, de mim, pois sou manso e humilde de coração.\"\nO caminho que Jesus deseja que seus discípulos sigam, é a sua própria vida. É o jogo da imitação. É você vivendo o que Cristo viveu. É você fazendo o que Cristo almeja.\nSer discípulo de Jesus é maravilhoso. Porque Ele se compadece de você no dia mau.\nÉ maravilhoso, porque Ele te ajuda, quando você reconhece as suas fraquezas.\nÉ maravilhoso porque Aquele que pode te condenar ao inferno, te pega pela mão e te dá uma nova chance.\nMuitas vezes, Ele nos dá uma nova oportunidade, cheia de graça e valor.\n\" Tomai de mim. Venham a mim todos que estão cansados e sobrecarregados.\"\nJesus não está prometendo inatividade e falta de problema. Está prometendo que se estivermos bem unidos a Ele, acharemos alívio em um mundo mau.\nDeus tem prazer em restaurar histórias.\nO chamado de Cristo nesta manhã, é que você tenha dois movimentos:\n1- Venha a mim.\n2- Tome sobre si a minha vida.\nNo primeiro movimento, você vai e Ele faz.\nNo segundo movimento, você toma e a partir daí, você verá a ação do Espírito Santo, transformando a sua história.\nHoje é o dia de deixar os fardos diante da cruz.\nO Senhor nos oportuniza momentos ímpares, ao longo do nosso ano. E nessa manhã, nós temos a oportunidade de vir até Jesus e colocar diante Dele os nossos fardos. E falar:\n\" Senhor, tira porque eu não consigo tirar. Tira porque eu quero experimentar o novo do Senhor em 2026. Tira e me dá o Seu fardo, o Seu jugo, para eu sair daqui e eu viva a vida que o Senhor espera de mim.\"\nPastor Gabriel Monteiro\nIBPS",
      "conteudo_limpo": "04/01/2026\n\"Ano Novo - Tempo de recomeçar \"\nMateus 11:28-30\nEis o contexto deste convite.\nO Senhor Jesus está falando dentro de uma realidade muito específica, mas que toca, o nosso tempo.\nEle está falando em um contexto, em que os religiosos daquele tempo, principalmente os fariseus, conhecedores da lei e rígidos no seu cumprimento e desdobramentos; e homens que colocavam fardos pesados, sobre os ombros de homens simples, trabalhadores. Homens decentes, mas que não conseguiriam cumprir tudo aquilo que a lei requeria. Religiosos que não conheciam de fato, a graça de Deus, mas colocavam peso extremo, que nem eles conseguiam cumprir, sobre a vida de homens e mulheres.\nQue ao olhar para a lei de Deus, se reconheciam como pecadores, como pequenos, como pessoas indignas.\nHomens que, ao olhar para as leis, perceberam quão estavam distantes daquilo que Deus espera.\nReconheceu algo que também precisamos - que Deus é Santo e nós somos pecadores!\nMas naquele contexto, o Senhor Jesus diz a esses homens:\n\" Eu espero dois movimentos de vocês. Porque eu tenho bênçãos. Eu tenho grandes coisas para fazer na vida de vocês.\"\nE o primeiro movimento de Jesus, Ele diz:\n\" Venham a mim!\"\nQuerido, o lugar do recomeço, é aos pés de Jesus.\nMuitas vezes estamos passando por dilemas, não sabemos por onde começar. Muitas vezes estamos passando por um caos familiar instaurado, já buscamos todo tipo de recursos, mas não viemos Àquele que pode resolver a nossa história!\nE o chamado de Jesus é para aqueles que estão cansados.\nTalvez você esteja cansado da lida da vida, das culpas, da amargura, da dificuldade de liberar perdão, do orgulho que corrói. Talvez você esteja cansado de cometer os mesmos pecados dia após dia. Talvez você esteja cansado de não conseguir sair desse lugar de maldição, que um dia você foi colocado.\nComo sair desse lugar e experimentar então, um recomeço?\nA resposta simples e clara do Evangelho - mergulhando na Graça de Deus.\nO chamado de Jesus é:\n\" Venha a mim \"\nEle não está dizendo:\nResolva as suas pendências, e depois venha a mim.\nEle está dizendo:\n\" Seja como for, seja como você estiver, com o fardo pesado na suas costas, venha a mim!\"\nVocê que se encontra inadequado, você que se encontra cheio de mágoas, você que se encontra cheio de culpas, você que se encontra cheio de pecados, você que já tentou de todas as formas, Ele diz:\n\" Se mova.\"\n\" Venha até mim para que eu mude a situação da sua história.\"\n\" Deixem que eu trabalhe em favor de vocês.\"\nIsaías 64:4\nO texto está falando que Deus trabalha, para aqueles que Nele esperam.\nÉ isso que Jesus Cristo está falando:\n\" Vinde a mim.\"\nVocê está cansado, porque você tenta do seu jeito.\nPara.\nNós somos filhos de Deus. Ele nos convoca a um relacionamento íntimo. A rasgar o coração. A se permitir ser tratado, ser cuidado. A saber que não é você que muda a sua história, mas é Deus, em Sua Graça e misericórdia.\nNós nos movemos, confiamos e esperamos, mas o trabalho é do Senhor.\nVocê está cansado, porque está trabalhando demais e confiando pouco.\nEsse é o problema.\nÉ exatamente isso que fazemos ao orar.\nA oração, é o homem inadequado, reconhecendo que precisa do mover de Deus na sua vida. É o reconhecimento de que se Deus não trabalhar ao nosso favor, em vão trabalharemos\nÀs vezes há o reconhecimento, mas não há o movimento.\nQual é o movimento?\n\"Venham a mim!\"\nSe permita ser tratado, se permita ser cuidado, se permita ser liberto.\nSalmos 50:15\nDeus e a pessoa que ora, são parceiros. Primeiro a sua parte - invocar o nome do Senhor. Depois, a parte de Deus - Eu o livrarei.\nNovamente a sua vez - receber essa graça. Depois, volta a vez para Deus - receber a Glória.\nAqui temos uma aliança, que Deus faz com você, enquanto você ora.\n\"Você terá o livramento e Eu terei a Glória.\"\n(Spurgeon)\nDeus é glorificado, enquanto trabalha em favor daqueles que O temem.\nEsse é o nosso Deus - Aquele que trabalha por aqueles que Nele esperam.\nPara recomeçar nesse novo ano, por que não vir até Jesus?\nExistem muitos crentes, que há anos estão tementes a Deus, mas que também estão precisando de um recomeço. Que se perderam no caminho, que sabemos que é longo.\nJesus está falando para você.\n\"Venha e encontre a transformação.\"\nA vida cristã não é uma corrida solo. É uma corrida acompanhada por Cristo.\nMateus 11:29\nExiste um segundo movimento - Tomar sobre si.\n\" Venha que Eu vou te dar o descanso.\"\nEle é um Deus que também nos chama a uma ação.\n\" Após eu fazer o extraordinário que você não consegue, existe uma ação que se espera de você.\nA fé cristã nos chama a um movimento.\n\" Eu vou tirar o jugo de vocês, para que você coloque o meu.\"\nComo é diferente o jugo de Jesus!\nÉ a plena confiança no Cristo Vivo.\nÉ um jugo onde somos imersos em meio a Graça e misericórdia.\nÉ um jugo onde somos ensinados a respeito daquele é Manso e Humilde de coração.\nColocar o fardo e o jugo de Jesus sobre nós, significa restaurar aquilo que nós somos e viver aquilo que nós fomos criados para viver.\nEle não retira o fardo e nos deixa inativos. Ele retira os fardos do pecado e coloca os seus.\nNo entanto, através da fé, nós percebemos como esses fardos são necessários para o nosso sustento.\nEm Cristo, nós encontramos o retirar do fardo, que aprisiona a alma. Nós encontramos o retirar da angústia, das mágoas, da culpa. Nós encontramos o retirar da dificuldade de perdoar. Nós retiramos o fardo da dificuldade de viver uma vida de integridade e encontramos então, um novo fardo. Mas um novo fardo, que nos faz ficar parecidos com Cristo dia após dia.\n\"Tome o meu jugo. Ele é suave, ele é leve. Aprendem, de mim, pois sou manso e humilde de coração.\"\nO caminho que Jesus deseja que seus discípulos sigam, é a sua própria vida. É o jogo da imitação. É você vivendo o que Cristo viveu. É você fazendo o que Cristo almeja.\nSer discípulo de Jesus é maravilhoso. Porque Ele se compadece de você no dia mau.\nÉ maravilhoso, porque Ele te ajuda, quando você reconhece as suas fraquezas.\nÉ maravilhoso porque Aquele que pode te condenar ao inferno, te pega pela mão e te dá uma nova chance.\nMuitas vezes, Ele nos dá uma nova oportunidade, cheia de graça e valor.\n\" Tomai de mim. Venham a mim todos que estão cansados e sobrecarregados.\"\nJesus não está prometendo inatividade e falta de problema. Está prometendo que se estivermos bem unidos a Ele, acharemos alívio em um mundo mau.\nDeus tem prazer em restaurar histórias.\nO chamado de Cristo nesta manhã, é que você tenha dois movimentos:\n1- Venha a mim.\n2- Tome sobre si a minha vida.\nNo primeiro movimento, você vai e Ele faz.\nNo segundo movimento, você toma e a partir daí, você verá a ação do Espírito Santo, transformando a sua história.\nHoje é o dia de deixar os fardos diante da cruz.\nO Senhor nos oportuniza momentos ímpares, ao longo do nosso ano. E nessa manhã, nós temos a oportunidade de vir até Jesus e colocar diante Dele os nossos fardos. E falar:\n\" Senhor, tira porque eu não consigo tirar. Tira porque eu quero experimentar o novo do Senhor em 2026. Tira e me dá o Seu fardo, o Seu jugo, para eu sair daqui e eu viva a vida que o Senhor espera de mim.\"\nPastor Gabriel Monteiro\nIBPS",
      "tamanho_texto": 7146,
      "url_blog": "https://pregacoesibps.blogspot.com/2026/01/ano-novo-tempo-de-recomecar-mateus-1128.html",
      "url_youtube": "",
      "tags": [],
      "_metadados": {
        "ano_arquivo": 2026,
        "igreja": "",
        "processado_em": "2026-01-16T13:57:17.385280",
        "data_fonte": "texto"
      },
      "id_unico": "2026_004",
      "metadados_biblicos": {
        "livro_principal": "Mateus",
        "texto_base": "Mateus 11:28-30",
        "total_referencias": 5,
        "referencias_titulo": 1,
        "referencias_conteudo": 4,
        "livros_mencionados": [
          "Mateus",
          "Salmos",
          "Isaías"
        ],
        "todas_referencias": [
          "Mateus 11:28-30",
          "Mateus 11:28-30",
          "Isaías 64:4",
          "Salmos 50:15",
          "Mateus 11:29"
        ]
      }
    },
    {
      "id_original": 5,
      "titulo": "Atos de gratidão - 1 Crônicas 29:10-20",
      "data_pregacao": "31/12/2025",
      "ano": 2025,
      "pregador": "Nélio Monteiro",
      "tipo_pregador": "oficial",
      "conteudo_original": "Resenha do Culto da Virada\n31/12/2025\nAtos de Gratidão\n1 Crônicas 29:10-20\nComo temos motivos para agradecer a Deus!\nComo igreja, muitos motivos!\nDeus abençoou todos os ministérios. Deus nos abençoou acrescentando vidas. Deus nos abençoou ouvindo nossas orações e continua nos abençoando ao longo dos dias.\nQuando Davi para, para refletir, a sua trajetória como pastor, como rei de Israel, como servo de Deus, ele faz uma pergunta para Deus:\n\"Que darei eu ao Senhor, por todos os benefícios que Ele me tem concedido?\"\nSalmos 116:12\nDavi era um homem grato.\nAlgo importante na vida do ser humano, é a gratidão.\nQuantas vezes, Deus nos abençoa ao longo dos anos!\nE quantas vezes, paramos para refletir, repensar na caminhada e expressar nossa gratidão pelo  cuidado do Senhor?\nDavi fazia isso.\nO texto está num contexto, em que Davi está olhando para sua trajetória.\nDavi está em fim de carreira.\nHá no seu coração, um desejo intenso.\n\"Ele habita num palácio e a arca da aliança, que representa a presença do Senhor, está numa tenda.\"\nNão pode ser assim! Pensa Davi.\nDavi reflete sobre isso. E vai ao conselheiro do reino, que o apoia.\nDavi fica muito contente e decide construir esse templo.\nMas Deus fala ao conselheiro espiritual do rei:\n\"Não, Davi não vai construir, porque Davi foi um homem de guerra. Derramou muito sangue.\"\nDe fato, Israel era constantemente atacado pelos seus inimigos.\nAlém de um grande rei, Davi foi um grande comandante.\nAgora Deus diz:\n\"Não vai ser você que vai construir, Davi. Teu filho que vai construir esse templo.\"\nE Davi começa a sonhar e a preparar recursos para que seu filho não encontrasse dificuldade em construir.\nArdia esse desejo no coração de Davi.\nPorque Davi reconhecia que tudo que tinha foi fruto da Graça de Deus.\nEle reconhece que foi Deus quem deu a vitória. Foi Deus quem fez a terra dar o fruto. Foi Deus quem fez a nação prosperar. Foi Deus quem lhe tirou do campo e colocou no trono de Israel. Ele tem consciência disso.\nÀs vezes nos esquecemos disso. De onde Deus nos buscou e onde Deus nos colocou.\nPor isso num ato de gratidão Davi deseja construir o templo.\nMas quando Deus disse que não seria ele,  Davi vai diante de seu povo e o conclama a levantar recursos para construir o grande templo de adoração a Deus.\nEo povo acompanha Davi.\nIsso alegra seu coração.\nA obra de Deus é feita com os recursos de Deus, como fruto da gratidão e fidelidade do povo de Deus a Deus.\nA obra de Deus  requer fé e sacrifício.\nNão conseguimos fazer a obra de Deus sem fé e sacrifício.\nDe cada ministério, de cada líder, Deus requer fé e sacrifício.\nDavi chama o povo a exercitar a fé e ao sacrifício.\nDavi chega a conclusão, que não temos como dar a Deus, nada que Deus não nos tenha dado.\nÉ isso que Davi reconhece.\nDeus se alegra quando reconhecemos a Sua Graça. Quando reconhecemos que tudo que nós temos foi Deus quem nos Deus. Que tudo que conquistamos é fruto da Graça de Deus.\nEssa é uma experiência sublime na nossa vida.\nGostaria de pensar três pontos na vivência de Davi:\n* Davi reconhece a Soberania de Deus.\n1 Crônicas 29:10-11\nDavi reconhece a Soberania de Deus. Por isso ele bendiz ao Senhor.\nDavi continua adorando a Deus.\nDeus é o Rei dos reis. Deus é Senhor dos senhores. Deus é Soberano em todo universo.\nO ser humano só encontra realização, sentido para sua vida, quando ele vive em íntima comunhão com Deus.\nQuando ele reconhece a Soberania de Deus sobre sua vida.\nIsso nos envolve.\nQuem era você? Onde Deus te encontrou?\nLembre-se:\nFoi Deus quem te deu a vida. Foi Deus quem te abençoou , quem te deu sabedoria. Foi Deus quem supriu, foi Deus quem abriu as portas.\nE temos que tomar um cuidado muito grande porque o mesmo Deus quem dá , também pode tirar.\nEle é Soberano.\n1 Crônicas 29:12\nRiquezas e glórias vem de Deus.\nSão presentes de Deus.\nO problema da humanidade é quando troca Deus, pelos presentes que Deus deu a ele.\nÉ quando aquilo que Deus deu para abençoar sua vida, é utilizado para levar o sujeito a se exaltar sobre Deus.\nA pensar que agora ele não precisa mais de Deus.\nQuantas vezes a gente ora, Deus abençoa e a benção afastou ele de Deus.\nPorque ele não reconheceu que foi Deus quem abençoou a vida dele. Que o domínio não está nas mãos do homem, o domínio está nas mãos de Deus.\nDavi reconhece que a força e o poder, está nas mãos de Deus.\nRei amado por toda nação. E é nesse momento que Davi olha e diz:\n\"Tudo eu devo a Deus.\nToda boa dádiva eu recebi da mão de Deus.\"\nÀs vezes fico pensando, onde Deus me buscou e onde Deus me colocou.\nDavi tinha essa consciência.\nTinha consciência da generosidade de Deus. E era grato.\nPorque Davi cometeu muitos erros na sua trajetória de vida.\nE como Deus foi paciente com Davi!\nComo Deus o corrigiu num ato de Graça! E Davi reconheceu isso também. Louvou e agradeceu a Deus no ato da correção.\nDavi só pediu a Deus:\n\"Não afaste, de mim o Teu Espírito.  Que eu não perca a minha alma.\"\nNessa vida podemos perder tudo, menos a nossa alma.\nE tem gente trocando a sua alma por tão pouco!\nDavi reconhecia que nada damos, que não tenhamos recebido.\n1 crônicas 29:14\nNós só entregamos aquilo que vem de Ti.\nO problema é quando nós retemos aquilo que vem de Deus.\nDeus nos abençoa para que possamos abençoar outros.\nDeus te coloca em lugares, para que você seja benção na vida de outros.\nHá uma alegria maior em nosso coração, quando nós oferecemos do que quando nós recebemos.\nNa vida de Davi tudo vem de Deus.\nNós só damos aquilo que vem das mãos de Deus.\nSe você está respirando hoje, é fruto da mão de Deus.\nSe Deus ouviu sua oração e respondeu trazendo a cura, abrindo portas, isso foi Graça de Deus.\nA mordomia, a fidelidade, é uma questão de gratidão.\nA fidelidade para com seu cônjuge é uma questão de gratidão.\nAo contrário, diz de um coração ingrato, que não reconhece a Graça de Deus na sua própria vida.\nDavi tem consciência de que a terra pertence ao Senhor. Que o fruto da terra pertence ao Senhor. Que nós devemos a Deus gratidão e adoração.\nDeus requer isso de nós. Deus requer fidelidade.\nFomos comprados por alto preço.\nJesus pagou por nós, Seu Precioso Sangue.\nDavi reconhece que somos peregrinos na terra.\n1 crônicas 29:15\nDavi reconhece que somos peregrinos nessa terra. Davi lembra como os nossos pais.\nSempre que um judeu está mencionando aos seus pais, ele está falando de Abraão, de Isaque e Jacó.\nMas, quantos anos, Abraão, Isaque e Jacó já tinham partido para eternidade!\nDavi está dizendo que nós somos peregrinos como eles.\nNossa vida nessa terra é como sombra.\nNós somos peregrinos. Nossos dias na terra, são como sombra. Os anos se sucedem. E um dia, nós também partiremos.\nPor que reter aquilo que pertence a Deus?\nPor que deixar de dar glória a Deus?\nPor que deixar de investir na obra de Deus no tempo oportuno?\nQuantas pessoas estão deixando para amanhã o abraço, o elogio, o fazer a obra com Deus.\nO tempo está passando. Não perca tempo.\nO abraço deve ser dado hoje. O reconhecimento deve ser dado hoje. A obra de Deus é para ser feita hoje. E não amanhã.\nNão retenha o que Deus te deu.\nOs recursos que Deus te deu, não são seus. São de Deus. Os filhos que Deus te deu, não são seus. São de Deus.\nIsso é reconhecer a Soberania de Deus.\n1 crônicas 29:17\nDeus ama a quem dá com alegria. Deus ama quem oferta com alegria.\nNão faça a obra de Deus murmurando.\nDeus quer que O adoremos e venhamos a servi-lo com alegria, voluntariamente.\nQuando reconheço tudo aquilo que Deus me deu, é um ato de gratidão.\nDavi diante de toda aquela manifestação de alegria, quando o povo levantou recursos para levantar o templo, Davi ora. Agora ele vai expressar sua gratidão a Deus.\n1 Crônicas 29:18\n\" Senhor mantém essa mesma disposição. Esse pensamento.\"\nEssa é minha oração. Quando vejo servos de Deus, servindo a Deus com seus dons, com seus talentos, com seus recursos, eu me alegro.\nEu sei do sacrifício daqueles que se envolvem.\nIsso alegra o coração de Deus. Esse é o verdadeiro culto a Deus.\nSou grato a Deus pela liderança. Por cada membro. Por todos os ministérios.\nPor fim, Davi ora por seu filho.\n1 crônicas 29:19\nFaço da oração de Davi a minha oração. Com algumas ressalvas.\nQue Deus dê aos meus filhos tanto biológicos, quanto os de coração, um coração íntegro para guardar os mandamentos do Senhor, para edificar a obra de Deus para a Glória de Deus.\"\nSe você fizer isso, 2026 será benção em sua vida. Você estará sob os cuidados de Deus e nós continuaremos avançando para a glória de Deus.\nPastor Nélio Monteiro\nIBPS",
      "conteudo_limpo": "31/12/2025\nAtos de Gratidão\n1 Crônicas 29:10-20\nComo temos motivos para agradecer a Deus!\nComo igreja, muitos motivos!\nDeus abençoou todos os ministérios. Deus nos abençoou acrescentando vidas. Deus nos abençoou ouvindo nossas orações e continua nos abençoando ao longo dos dias.\nQuando Davi para, para refletir, a sua trajetória como pastor, como rei de Israel, como servo de Deus, ele faz uma pergunta para Deus:\n\"Que darei eu ao Senhor, por todos os benefícios que Ele me tem concedido?\"\nSalmos 116:12\nDavi era um homem grato.\nAlgo importante na vida do ser humano, é a gratidão.\nQuantas vezes, Deus nos abençoa ao longo dos anos!\nE quantas vezes, paramos para refletir, repensar na caminhada e expressar nossa gratidão pelo  cuidado do Senhor?\nDavi fazia isso.\nO texto está num contexto, em que Davi está olhando para sua trajetória.\nDavi está em fim de carreira.\nHá no seu coração, um desejo intenso.\n\"Ele habita num palácio e a arca da aliança, que representa a presença do Senhor, está numa tenda.\"\nNão pode ser assim! Pensa Davi.\nDavi reflete sobre isso. E vai ao conselheiro do reino, que o apoia.\nDavi fica muito contente e decide construir esse templo.\nMas Deus fala ao conselheiro espiritual do rei:\n\"Não, Davi não vai construir, porque Davi foi um homem de guerra. Derramou muito sangue.\"\nDe fato, Israel era constantemente atacado pelos seus inimigos.\nAlém de um grande rei, Davi foi um grande comandante.\nAgora Deus diz:\n\"Não vai ser você que vai construir, Davi. Teu filho que vai construir esse templo.\"\nE Davi começa a sonhar e a preparar recursos para que seu filho não encontrasse dificuldade em construir.\nArdia esse desejo no coração de Davi.\nPorque Davi reconhecia que tudo que tinha foi fruto da Graça de Deus.\nEle reconhece que foi Deus quem deu a vitória. Foi Deus quem fez a terra dar o fruto. Foi Deus quem fez a nação prosperar. Foi Deus quem lhe tirou do campo e colocou no trono de Israel. Ele tem consciência disso.\nÀs vezes nos esquecemos disso. De onde Deus nos buscou e onde Deus nos colocou.\nPor isso num ato de gratidão Davi deseja construir o templo.\nMas quando Deus disse que não seria ele,  Davi vai diante de seu povo e o conclama a levantar recursos para construir o grande templo de adoração a Deus.\nEo povo acompanha Davi.\nIsso alegra seu coração.\nA obra de Deus é feita com os recursos de Deus, como fruto da gratidão e fidelidade do povo de Deus a Deus.\nA obra de Deus  requer fé e sacrifício.\nNão conseguimos fazer a obra de Deus sem fé e sacrifício.\nDe cada ministério, de cada líder, Deus requer fé e sacrifício.\nDavi chama o povo a exercitar a fé e ao sacrifício.\nDavi chega a conclusão, que não temos como dar a Deus, nada que Deus não nos tenha dado.\nÉ isso que Davi reconhece.\nDeus se alegra quando reconhecemos a Sua Graça. Quando reconhecemos que tudo que nós temos foi Deus quem nos Deus. Que tudo que conquistamos é fruto da Graça de Deus.\nEssa é uma experiência sublime na nossa vida.\nGostaria de pensar três pontos na vivência de Davi:\n* Davi reconhece a Soberania de Deus.\n1 Crônicas 29:10-11\nDavi reconhece a Soberania de Deus. Por isso ele bendiz ao Senhor.\nDavi continua adorando a Deus.\nDeus é o Rei dos reis. Deus é Senhor dos senhores. Deus é Soberano em todo universo.\nO ser humano só encontra realização, sentido para sua vida, quando ele vive em íntima comunhão com Deus.\nQuando ele reconhece a Soberania de Deus sobre sua vida.\nIsso nos envolve.\nQuem era você? Onde Deus te encontrou?\nLembre-se:\nFoi Deus quem te deu a vida. Foi Deus quem te abençoou , quem te deu sabedoria. Foi Deus quem supriu, foi Deus quem abriu as portas.\nE temos que tomar um cuidado muito grande porque o mesmo Deus quem dá , também pode tirar.\nEle é Soberano.\n1 Crônicas 29:12\nRiquezas e glórias vem de Deus.\nSão presentes de Deus.\nO problema da humanidade é quando troca Deus, pelos presentes que Deus deu a ele.\nÉ quando aquilo que Deus deu para abençoar sua vida, é utilizado para levar o sujeito a se exaltar sobre Deus.\nA pensar que agora ele não precisa mais de Deus.\nQuantas vezes a gente ora, Deus abençoa e a benção afastou ele de Deus.\nPorque ele não reconheceu que foi Deus quem abençoou a vida dele. Que o domínio não está nas mãos do homem, o domínio está nas mãos de Deus.\nDavi reconhece que a força e o poder, está nas mãos de Deus.\nRei amado por toda nação. E é nesse momento que Davi olha e diz:\n\"Tudo eu devo a Deus.\nToda boa dádiva eu recebi da mão de Deus.\"\nÀs vezes fico pensando, onde Deus me buscou e onde Deus me colocou.\nDavi tinha essa consciência.\nTinha consciência da generosidade de Deus. E era grato.\nPorque Davi cometeu muitos erros na sua trajetória de vida.\nE como Deus foi paciente com Davi!\nComo Deus o corrigiu num ato de Graça! E Davi reconheceu isso também. Louvou e agradeceu a Deus no ato da correção.\nDavi só pediu a Deus:\n\"Não afaste, de mim o Teu Espírito.  Que eu não perca a minha alma.\"\nNessa vida podemos perder tudo, menos a nossa alma.\nE tem gente trocando a sua alma por tão pouco!\nDavi reconhecia que nada damos, que não tenhamos recebido.\n1 crônicas 29:14\nNós só entregamos aquilo que vem de Ti.\nO problema é quando nós retemos aquilo que vem de Deus.\nDeus nos abençoa para que possamos abençoar outros.\nDeus te coloca em lugares, para que você seja benção na vida de outros.\nHá uma alegria maior em nosso coração, quando nós oferecemos do que quando nós recebemos.\nNa vida de Davi tudo vem de Deus.\nNós só damos aquilo que vem das mãos de Deus.\nSe você está respirando hoje, é fruto da mão de Deus.\nSe Deus ouviu sua oração e respondeu trazendo a cura, abrindo portas, isso foi Graça de Deus.\nA mordomia, a fidelidade, é uma questão de gratidão.\nA fidelidade para com seu cônjuge é uma questão de gratidão.\nAo contrário, diz de um coração ingrato, que não reconhece a Graça de Deus na sua própria vida.\nDavi tem consciência de que a terra pertence ao Senhor. Que o fruto da terra pertence ao Senhor. Que nós devemos a Deus gratidão e adoração.\nDeus requer isso de nós. Deus requer fidelidade.\nFomos comprados por alto preço.\nJesus pagou por nós, Seu Precioso Sangue.\nDavi reconhece que somos peregrinos na terra.\n1 crônicas 29:15\nDavi reconhece que somos peregrinos nessa terra. Davi lembra como os nossos pais.\nSempre que um judeu está mencionando aos seus pais, ele está falando de Abraão, de Isaque e Jacó.\nMas, quantos anos, Abraão, Isaque e Jacó já tinham partido para eternidade!\nDavi está dizendo que nós somos peregrinos como eles.\nNossa vida nessa terra é como sombra.\nNós somos peregrinos. Nossos dias na terra, são como sombra. Os anos se sucedem. E um dia, nós também partiremos.\nPor que reter aquilo que pertence a Deus?\nPor que deixar de dar glória a Deus?\nPor que deixar de investir na obra de Deus no tempo oportuno?\nQuantas pessoas estão deixando para amanhã o abraço, o elogio, o fazer a obra com Deus.\nO tempo está passando. Não perca tempo.\nO abraço deve ser dado hoje. O reconhecimento deve ser dado hoje. A obra de Deus é para ser feita hoje. E não amanhã.\nNão retenha o que Deus te deu.\nOs recursos que Deus te deu, não são seus. São de Deus. Os filhos que Deus te deu, não são seus. São de Deus.\nIsso é reconhecer a Soberania de Deus.\n1 crônicas 29:17\nDeus ama a quem dá com alegria. Deus ama quem oferta com alegria.\nNão faça a obra de Deus murmurando.\nDeus quer que O adoremos e venhamos a servi-lo com alegria, voluntariamente.\nQuando reconheço tudo aquilo que Deus me deu, é um ato de gratidão.\nDavi diante de toda aquela manifestação de alegria, quando o povo levantou recursos para levantar o templo, Davi ora. Agora ele vai expressar sua gratidão a Deus.\n1 Crônicas 29:18\n\" Senhor mantém essa mesma disposição. Esse pensamento.\"\nEssa é minha oração. Quando vejo servos de Deus, servindo a Deus com seus dons, com seus talentos, com seus recursos, eu me alegro.\nEu sei do sacrifício daqueles que se envolvem.\nIsso alegra o coração de Deus. Esse é o verdadeiro culto a Deus.\nSou grato a Deus pela liderança. Por cada membro. Por todos os ministérios.\nPor fim, Davi ora por seu filho.\n1 crônicas 29:19\nFaço da oração de Davi a minha oração. Com algumas ressalvas.\nQue Deus dê aos meus filhos tanto biológicos, quanto os de coração, um coração íntegro para guardar os mandamentos do Senhor, para edificar a obra de Deus para a Glória de Deus.\"\nSe você fizer isso, 2026 será benção em sua vida. Você estará sob os cuidados de Deus e nós continuaremos avançando para a glória de Deus.\nPastor Nélio Monteiro\nIBPS",
      "tamanho_texto": 8462,
      "url_blog": "https://pregacoesibps.blogspot.com/2026/01/atos-de-gratidao-1-cronicas-2910-20.html",
      "url_youtube": "",
      "tags": [],
      "_metadados": {
        "ano_arquivo": 2026,
        "igreja": "",
        "processado_em": "2026-01-16T13:57:17.385991",
        "data_fonte": "texto"
      },
      "id_unico": "2025_005",
      "metadados_biblicos": {
        "livro_principal": "Salmos",
        "texto_base": null,
        "total_referencias": 1,
        "referencias_titulo": 0,
        "referencias_conteudo": 1,
        "livros_mencionados": [
          "Salmos"
        ],
        "todas_referencias": [
          "Salmos 116:12"
        ]
      }
    },
    {
      "id_original": 6,
      "titulo": "Apocalipse - Pérgamo somos nós ( Apocalipse 2:12-17)",
      "data_pregacao": "07/01/2025",
      "ano": 2025,
      "pregador": "Ryan Souza",
      "tipo_pregador": "oficial",
      "conteudo_original": "Resenha do Culto de quarta-feira\n07/01/2025\n\"Apocalipse - Pérgamo somos nós\"\nApocalipse 2:12-17\nAo expor o nosso pecado, Cristo oferece também, oportunidade de cura e de restauração. Ao expor os nossos erros, as nossas falhas, aqueles pontos cegos que muitas ou algumas vezes não enxergamos. Isso Davi ora.\nQuando Cristo nos aponta os nossos pecados, vem com esse apontamento também, uma grande oportunidade de cura e restauração.\nPor isso, fazemos bem, em todas as vezes que chegamos a esse lugar, para ouvir atentamente a Palavra de Deus.\nPor isso, nós fazemos bem, em olhar para a Palavra de Deus e olhando para a Palavra de Deus, olhar também para as nossas vidas e verificar o que precisa ser corrigido, aquilo que precisa ser transformado, ajustado com a realidade da  Palavra de Deus.\nPara verificarmos, se aquilo que nós ouvimos através da Palavra de Deus, aquilo que nós falamos que cremos, se encaixa com aquilo que vivemos.\nEsse é o grande desafio, todas as vezes que lemos ou ouvimos a Palavra.\nPorque quando lemos a Palavra, ela nos lê. Ela lê as nossas vidas.\nE esse é um exercício importantíssimo para nossa vitalidade espiritual.\nQuando pensamos em nossa vida, todos nós, em algum momento, precisou recomeçar ou abandonar coisas. Trazendo mais leveza para a nossa viagem.\nEssa era a importância daquelas cartas, para aquelas comunidades.\nPorque havia coisas que Cristo queria restaurar naqueles irmãos,  naquelas igrejas.\nÉ por isso que quando olhamos para esse texto, entendemos que essas advertências, encaixam nas nossas vidas.\nO que Deus está falando comigo aqui?\nComo lidamos com as advertências que Deus traz a nós?\nEsse texto, são advertências de Deus a nós.\nÉ o Cristo amoroso que traz as suas advertências para nós.\nComo você lida com as advertências de Deus, através da Sua Palavra?\nComo esse texto reflete na sua vida diária?\nPérgamo era um lugar hostil a fé.\nImagine uma igreja localizada, onde o Próprio Cristo vai falar que ali também, está localizado o trono de satanás!\nEssa cidade foi a capital da Ásia por quatrocentos anos.\nEla era uma cidade importantíssima, sobretudo no ponto cultural.\nEla abrigava uma das maiores bibliotecas.\nAli abrigava vários templos de deuses pagãos.\nMuitas pessoas faziam suas caravanas, para estar nestes templos e fazer sacrifícios a esse deus.\nTratavam também César, como um deus.\nNesse lugar, ser crente custava alguma coisa. Era desafiador.\nSe identificar com Cristo, poderia significar algum martírio.\nOs crentes também eram convocados a prestar tributo, a chamar Cesar de senhor. Eram convocados a queimar incenso a César, anualmente.\nAqueles que se recusassem a isso, pagariam com a própria vida.\nSer crente em Pérgamo, era algo custoso.\nDesde quando, o nosso cristianismo deixou de custar algo?\nDesde quando, ser crente, deixou de custar algo?\nAtualmente vemos pessoas entrando nas igrejas, se professam cristãos, vivendo uma fé que não lhes custa absolutamente nada.\nAs pessoas pensam que podem servir a Cristo, sem nenhum tipo de sacrifício em suas vidas, sem abandonar hábitos pecaminosos, más amizades.\nVocê já parou para pensar, no ambiente que você está inserido?\nQuem são as pessoas que convivemos?\nAs influências, os desafios, os deuses que se apresentam com outras roupagens, as ideologias que nos cercam?\nMe parece, que perdemos esse discernimento. É por isso, que vemos muitos crentes, vivendo de qualquer forma. Sem avaliar, o custo que servir a Deus faz.\nCaminhamos como se não estivéssemos num mundo hostil, a Cristo e a nós.\nSe você não sente o peso de ser um cristão, alguma coisa está errada.\nO mundo jaz no maligno.\nComo podemos identificar as Palavras de Cristo a nós?\nAquela igreja estava num ambiente hostil.\nJesus até elogia aquela igreja! Que no meio disso tudo, estavam se mantendo firmes. Estavam se mantendo fiéis.\nEle cita aqui, Antipas, um homem valoroso, de fé inabalável, que suportou o preço do cristianismo.\nÀs vezes, as pessoas vivem o cristianismo há tanto tempo, e você nem percebe que ela abandonou coisas. Ainda está com a mochila pesada.\nJesus vai falar de um homem chamado Antipas, que se mostrou valoroso, pelo fato de que ele foi até às últimas consequências em ser cristão.\nMorreu assado em um touro de bronze.\nA gente olha para esses homens que se recusaram a  queimar incensos, e dizer que César é Senhor, e nós pensamos:\n\" Como nosso cristianismo é pobre. Não nos custa muita coisa.\"\nCristo elogia os irmãos que estavam em lugar hostil, mas traz também as Suas advertências.\nApocalipse 2:14-15\nAgora ele está falando para uma outra igreja.\nJesus condena Pérgamo, por sua tolerância aos falsos mestres, as falsas doutrinas e práticas imorais e pecaminosas.\nUm crente mal doutrinado, não tem como ser um crente frutífero.\nDoutrinas incorretas, práticas erradas.\nPor isso que Jesus vai advertir aqueles que estavam tolerando falsos ensinos. Alguns desses irmãos, adeptos inclusive, do erro de Balaão.\nBalaão foi um falso profeta.\nUm profeta de Deus que se vendeu. Cedeu a sua ganância, a sua cobiça.\nFoi impedido pelo Senhor de profetizar negativamente contra o povo.\nSeus conselhos satânicos, trouxe consequências para o povo de Deus.\nJesus cita também um grupo, que defendia essa vida licenciada. Essa vida libertina, junto com a vida cristã.  Pessoas que domingo estão na igreja, segunda já não são crentes.\nJesus vai advertir, que eles estavam sustentando um tipo de doutrina, que pregava um cristianismo permissivo, influenciável pela sua cultura, por práticas pagãs imorais.\nAquela igreja tinha abraçado o modo de pensar e de agir, do mundo.\nAquela igreja estava dessa forma.\nAlguns daqueles, quem sabe, caminhavam para se tornar uma igreja mundana.\nPor isso, a advertência de Cristo àquela comunidade.\nFico pensando que Deus sempre interrompe o nosso pecado.\nDeus sempre vai achar um jeito, através da Sua Palavra, de confrontar o nosso pecado.\nNão vai nos deixar pecar em paz.\nPor isso, a importância de olharmos para a Palavra de Deus e analisarmos a nossa vida.\n\"Senhor, me mostra em que preciso mudar!\"\nHoje também vivemos na Babilônia.\nNão vemos os templos erigidos a Zeus, a Diana ... Mas será que nós não temos também, uns falsos deuses, querendo um pedacinho da nossa adoração?\nA acusação de Cristo vem contra isso.\nPorque eles estavam flertando com o pecado. Estavam dispostos a trilhar o caminho mais fácil.\nPor isso, o Senhor acusa os cristãos de Pérgamo de cometer prostituição ou adultério espiritual - dizendo CESAR É SENHOR.\nHoje também, somos tentados a escolher o caminho mais fácil.\nA escolhermos o discipulado sem cruz. Sem custo, sem abandono.\nTodos nós somos atacados por essa tentação, de escolher o caminho mais fácil. Fazendo concessões.\nAQUELE que sonda as intenções do coração, chama aquela igreja a uma mudança - Reavaliar a sua vida. Provar a Sua doutrina, corrigir os seus erros.\nApocalipse 2:16\nQual é o convite da graça?\nArrependa-se.\nComeçamos o ano pensando nessas duas coisas:\nRecomeçar e abandonar.\nAo olhar para essa carta e também para as outras, conseguiremos  identificar esse apelo do Senhor a nós.\n\"Arrependam-se. Mudem a rota de vocês.\"\nAo expor o nosso pecado, Cristo oferece a oportunidade de cura, de restauração , de mudança, de arrependimento.\nComo temos ouvido as advertências do Próprio Cristo?\nComo recebemos o convite de Cristo a nós?\nDeus deu ao seu povo, profetas. A palavra que ecoa em todas as profecias é:\n\" Arrependam-se\"\nQuando João Batista começa falando, qual a mensagem que ele tem:\n\"Arrependa-se! Endireitai o caminho.\"\nEssa mensagem, que chega até nós nessa noite.\nPastor Ryan Sousa\nIBPS",
      "conteudo_limpo": "07/01/2025\n\"Apocalipse - Pérgamo somos nós\"\nApocalipse 2:12-17\nAo expor o nosso pecado, Cristo oferece também, oportunidade de cura e de restauração. Ao expor os nossos erros, as nossas falhas, aqueles pontos cegos que muitas ou algumas vezes não enxergamos. Isso Davi ora.\nQuando Cristo nos aponta os nossos pecados, vem com esse apontamento também, uma grande oportunidade de cura e restauração.\nPor isso, fazemos bem, em todas as vezes que chegamos a esse lugar, para ouvir atentamente a Palavra de Deus.\nPor isso, nós fazemos bem, em olhar para a Palavra de Deus e olhando para a Palavra de Deus, olhar também para as nossas vidas e verificar o que precisa ser corrigido, aquilo que precisa ser transformado, ajustado com a realidade da  Palavra de Deus.\nPara verificarmos, se aquilo que nós ouvimos através da Palavra de Deus, aquilo que nós falamos que cremos, se encaixa com aquilo que vivemos.\nEsse é o grande desafio, todas as vezes que lemos ou ouvimos a Palavra.\nPorque quando lemos a Palavra, ela nos lê. Ela lê as nossas vidas.\nE esse é um exercício importantíssimo para nossa vitalidade espiritual.\nQuando pensamos em nossa vida, todos nós, em algum momento, precisou recomeçar ou abandonar coisas. Trazendo mais leveza para a nossa viagem.\nEssa era a importância daquelas cartas, para aquelas comunidades.\nPorque havia coisas que Cristo queria restaurar naqueles irmãos,  naquelas igrejas.\nÉ por isso que quando olhamos para esse texto, entendemos que essas advertências, encaixam nas nossas vidas.\nO que Deus está falando comigo aqui?\nComo lidamos com as advertências que Deus traz a nós?\nEsse texto, são advertências de Deus a nós.\nÉ o Cristo amoroso que traz as suas advertências para nós.\nComo você lida com as advertências de Deus, através da Sua Palavra?\nComo esse texto reflete na sua vida diária?\nPérgamo era um lugar hostil a fé.\nImagine uma igreja localizada, onde o Próprio Cristo vai falar que ali também, está localizado o trono de satanás!\nEssa cidade foi a capital da Ásia por quatrocentos anos.\nEla era uma cidade importantíssima, sobretudo no ponto cultural.\nEla abrigava uma das maiores bibliotecas.\nAli abrigava vários templos de deuses pagãos.\nMuitas pessoas faziam suas caravanas, para estar nestes templos e fazer sacrifícios a esse deus.\nTratavam também César, como um deus.\nNesse lugar, ser crente custava alguma coisa. Era desafiador.\nSe identificar com Cristo, poderia significar algum martírio.\nOs crentes também eram convocados a prestar tributo, a chamar Cesar de senhor. Eram convocados a queimar incenso a César, anualmente.\nAqueles que se recusassem a isso, pagariam com a própria vida.\nSer crente em Pérgamo, era algo custoso.\nDesde quando, o nosso cristianismo deixou de custar algo?\nDesde quando, ser crente, deixou de custar algo?\nAtualmente vemos pessoas entrando nas igrejas, se professam cristãos, vivendo uma fé que não lhes custa absolutamente nada.\nAs pessoas pensam que podem servir a Cristo, sem nenhum tipo de sacrifício em suas vidas, sem abandonar hábitos pecaminosos, más amizades.\nVocê já parou para pensar, no ambiente que você está inserido?\nQuem são as pessoas que convivemos?\nAs influências, os desafios, os deuses que se apresentam com outras roupagens, as ideologias que nos cercam?\nMe parece, que perdemos esse discernimento. É por isso, que vemos muitos crentes, vivendo de qualquer forma. Sem avaliar, o custo que servir a Deus faz.\nCaminhamos como se não estivéssemos num mundo hostil, a Cristo e a nós.\nSe você não sente o peso de ser um cristão, alguma coisa está errada.\nO mundo jaz no maligno.\nComo podemos identificar as Palavras de Cristo a nós?\nAquela igreja estava num ambiente hostil.\nJesus até elogia aquela igreja! Que no meio disso tudo, estavam se mantendo firmes. Estavam se mantendo fiéis.\nEle cita aqui, Antipas, um homem valoroso, de fé inabalável, que suportou o preço do cristianismo.\nÀs vezes, as pessoas vivem o cristianismo há tanto tempo, e você nem percebe que ela abandonou coisas. Ainda está com a mochila pesada.\nJesus vai falar de um homem chamado Antipas, que se mostrou valoroso, pelo fato de que ele foi até às últimas consequências em ser cristão.\nMorreu assado em um touro de bronze.\nA gente olha para esses homens que se recusaram a  queimar incensos, e dizer que César é Senhor, e nós pensamos:\n\" Como nosso cristianismo é pobre. Não nos custa muita coisa.\"\nCristo elogia os irmãos que estavam em lugar hostil, mas traz também as Suas advertências.\nApocalipse 2:14-15\nAgora ele está falando para uma outra igreja.\nJesus condena Pérgamo, por sua tolerância aos falsos mestres, as falsas doutrinas e práticas imorais e pecaminosas.\nUm crente mal doutrinado, não tem como ser um crente frutífero.\nDoutrinas incorretas, práticas erradas.\nPor isso que Jesus vai advertir aqueles que estavam tolerando falsos ensinos. Alguns desses irmãos, adeptos inclusive, do erro de Balaão.\nBalaão foi um falso profeta.\nUm profeta de Deus que se vendeu. Cedeu a sua ganância, a sua cobiça.\nFoi impedido pelo Senhor de profetizar negativamente contra o povo.\nSeus conselhos satânicos, trouxe consequências para o povo de Deus.\nJesus cita também um grupo, que defendia essa vida licenciada. Essa vida libertina, junto com a vida cristã.  Pessoas que Jesus vai advertir, que eles estavam sustentando um tipo de doutrina, que pregava um cristianismo permissivo, influenciável pela sua cultura, por práticas pagãs imorais.\nAquela igreja tinha abraçado o modo de pensar e de agir, do mundo.\nAquela igreja estava dessa forma.\nAlguns daqueles, quem sabe, caminhavam para se tornar uma igreja mundana.\nPor isso, a advertência de Cristo àquela comunidade.\nFico pensando que Deus sempre interrompe o nosso pecado.\nDeus sempre vai achar um jeito, através da Sua Palavra, de confrontar o nosso pecado.\nNão vai nos deixar pecar em paz.\nPor isso, a importância de olharmos para a Palavra de Deus e analisarmos a nossa vida.\n\"Senhor, me mostra em que preciso mudar!\"\nHoje também vivemos na Babilônia.\nNão vemos os templos erigidos a Zeus, a Diana ... Mas será que nós não temos também, uns falsos deuses, querendo um pedacinho da nossa adoração?\nA acusação de Cristo vem contra isso.\nPorque eles estavam flertando com o pecado. Estavam dispostos a trilhar o caminho mais fácil.\nPor isso, o Senhor acusa os cristãos de Pérgamo de cometer prostituição ou adultério espiritual - dizendo CESAR É SENHOR.\nHoje também, somos tentados a escolher o caminho mais fácil.\nA escolhermos o discipulado sem cruz. Sem custo, sem abandono.\nTodos nós somos atacados por essa tentação, de escolher o caminho mais fácil. Fazendo concessões.\nAQUELE que sonda as intenções do coração, chama aquela igreja a uma mudança - Reavaliar a sua vida. Provar a Sua doutrina, corrigir os seus erros.\nApocalipse 2:16\nQual é o convite da graça?\nArrependa-se.\nComeçamos o ano pensando nessas duas coisas:\nRecomeçar e abandonar.\nAo olhar para essa carta e também para as outras, conseguiremos  identificar esse apelo do Senhor a nós.\n\"Arrependam-se. Mudem a rota de vocês.\"\nAo expor o nosso pecado, Cristo oferece a oportunidade de cura, de restauração , de mudança, de arrependimento.\nComo temos ouvido as advertências do Próprio Cristo?\nComo recebemos o convite de Cristo a nós?\nDeus deu ao seu povo, profetas. A palavra que ecoa em todas as profecias é:\n\" Arrependam-se\"\nQuando João Batista começa falando, qual a mensagem que ele tem:\n\"Arrependa-se! Endireitai o caminho.\"\nEssa mensagem, que chega até nós nessa noite.\nPastor Ryan Sousa\nIBPS",
      "tamanho_texto": 7570,
      "url_blog": "https://pregacoesibps.blogspot.com/2026/01/apocalipse-pergamo-somos-nos-apocalipse.html",
      "url_youtube": "",
      "tags": [],
      "_metadados": {
        "ano_arquivo": 2026,
        "igreja": "",
        "processado_em": "2026-01-16T13:57:17.386737",
        "data_fonte": "texto"
      },
      "id_unico": "2025_006",
      "metadados_biblicos": {
        "livro_principal": "Apocalipse",
        "texto_base": "Apocalipse 2:12-17",
        "total_referencias": 4,
        "referencias_titulo": 1,
        "referencias_conteudo": 3,
        "livros_mencionados": [
          "Apocalipse"
        ],
        "todas_referencias": [
          "Apocalipse 2:12-17",
          "Apocalipse 2:12-17",
          "Apocalipse 2:14-15",
          "Apocalipse 2:16"
        ]
      }
    },
    {
      "id_original": 7,
      "titulo": "Lucas 17:11-19",
      "data_pregacao": null,
      "ano": 2026,
      "pregador": "Gabriel Monteiro",
      "tipo_pregador": "oficial",
      "conteudo_original": "Lucas 17:11-19\nEstamos diante de um texto que fala muito, a respeito de gratidão.\nGratidão a Deus pelo que Ele tem feito. Pelo que Ele é. Gratidão a Deus pelos Seus grandes e maravilhosos feitos em nossas vidas.\nSe você parar para pensar, você tem muito que agradecer a Deus.\nSe o ano foi difícil, se foi extraordinário, nós devemos agradecer a Deus.\nNesse texto bíblico, estamos diante de uma representação do que nós somos.\nO texto nos apresenta dez leprosos.\nQue estavam na condição de verdadeiros mortos vivos.\nHoje a lepra tem cura. Mas naquele tempo, a medicina  não tinha o que fazer.\nEram homens que eram colocados a parte da sociedade.  Viviam grandes problemas.\nNaquele dia especial, Jesus passou por aquela região. E aqueles dez leprosos vão até Jesus, clamando por compaixão.\nEu não sei o que você viveu esse ano. Mas muitas vezes nossa fala com Jesus é:\n\"Senhor tem compaixão de mim.\"\nMuitas vezes estamos aqui para agradecer e  também para clamar.\nAo se encontrar com Jesus, algo extraordinário acontece.\nE Jesus olha para aqueles homens e dá um direcionamento.\n\" Vá se apresentar aos sacerdotes.\"\nNós vemos Jesus ministrando a cura na hora. Mas desta vez, algo diferente está acontecendo.\nMuitas vezes, recebemos direcionamentos assim, de Deus.\nQueremos o milagre na hora, mas Deus nos diz para seguir o caminho.\nO texto nos diz que aqueles homens continuam avançando.\nEnquanto estão caminhando,  os dez são curados.\nO milagre acontece, enquanto eles se põe, a avançar.\nNesse novo ano, temos a oportunidade de ouvir o direcionamento do Mestre e continuar avançando.\nPrecisamos olhar além.\nQuando esses homens olham além, o milagre acontece. Eles são curados.\nEles recebem as\nbençãos\nde Deus. O milagre de Cristo. Estão curados.\nSeus sonhos estavam mortos.\nDiante dessa alegria, apenas um deles retorna até Jesus.\nUm homem. O mais improvável de todos, pois era samaritano. Esse homem volta aos pés de Cristo, em gratidão por tudo que Deus fez.\nA gratidão transforma nossa vida. Liberta nosso coração amargurado. A gratidão quebra muralhas, a gratidão evita pecados.\nReclamamos por tudo!\nMas, e a gratidão?\nE a gratidão por tudo aquilo que Deus fez, pelos detalhes, pela generosidade da mesa farta, pelas amizades, pela Palavra de Deus ministrada aos corações, pela saúde de poder findar o ano na presença de Deus?!\nE a gratidão por lembrar que esse Deus enviou o Seu Filho para morrer na cruz, para que tenhamos a vida eterna?!\nE a gratidão pelas batalhas, pelas portas fechadas, por Deus dizer não e você depois olhar e dizer como foi cuidado por Deus?!\nPrecisamos mudar uma cultura de murmuração por uma cultura de gratidão.\nO que faremos agora é um ato de gratidão. É um ato de reconhecimento, de que pelo Corpo e Sangue de Cristo Jesus, nós fomos sarados.\nA Ceia do Senhor é a clara lembrança,de que no passado Deus fez por nós. De que no presente Deus faz por nós. De que o futuro está garantido, porque Deus assim garantiu, mediante a Sua Palavra e mediante o sacrifício de Seu Filho.\nEstamos reunidos em profunda gratidão.\nDaqueles dez, um voltou para agradecer.\nNove homens foram curados da lepra, mas um homem foi curado da lepra e teve naquele dia,  a salvação da sua alma.\nEstamos aqui para celebrar, que um dia, nós também, tivemos a nossa alma curada, resgatada, redimida e assim podemos entrar no novo ano, aguardando o retorno do nosso Salvador.\nPastor Gabriel Monteiro\nIBPS",
      "conteudo_limpo": "Lucas 17:11-19\nEstamos diante de um texto que fala muito, a respeito de gratidão.\nGratidão a Deus pelo que Ele tem feito. Pelo que Ele é. Gratidão a Deus pelos Seus grandes e maravilhosos feitos em nossas vidas.\nSe você parar para pensar, você tem muito que agradecer a Deus.\nSe o ano foi difícil, se foi extraordinário, nós devemos agradecer a Deus.\nNesse texto bíblico, estamos diante de uma representação do que nós somos.\nO texto nos apresenta dez leprosos.\nQue estavam na condição de verdadeiros mortos vivos.\nHoje a lepra tem cura. Mas naquele tempo, a medicina  não tinha o que fazer.\nEram homens que eram colocados a parte da sociedade.  Viviam grandes problemas.\nNaquele dia especial, Jesus passou por aquela região. E aqueles dez leprosos vão até Jesus, clamando por compaixão.\nEu não sei o que você viveu esse ano. Mas muitas vezes nossa fala com Jesus é:\n\"Senhor tem compaixão de mim.\"\nMuitas vezes estamos aqui para agradecer e  também para clamar.\nAo se encontrar com Jesus, algo extraordinário acontece.\nE Jesus olha para aqueles homens e dá um direcionamento.\n\" Vá se apresentar aos sacerdotes.\"\nNós vemos Jesus ministrando a cura na hora. Mas desta vez, algo diferente está acontecendo.\nMuitas vezes, recebemos direcionamentos assim, de Deus.\nQueremos o milagre na hora, mas Deus nos diz para seguir o caminho.\nO texto nos diz que aqueles homens continuam avançando.\nEnquanto estão caminhando,  os dez são curados.\nO milagre acontece, enquanto eles se põe, a avançar.\nNesse novo ano, temos a oportunidade de ouvir o direcionamento do Mestre e continuar avançando.\nPrecisamos olhar além.\nQuando esses homens olham além, o milagre acontece. Eles são curados.\nEles recebem as\nbençãos\nde Deus. O milagre de Cristo. Estão curados.\nSeus sonhos estavam mortos.\nDiante dessa alegria, apenas um deles retorna até Jesus.\nUm homem. O mais improvável de todos, pois era samaritano. Esse homem volta aos pés de Cristo, em gratidão por tudo que Deus fez.\nA gratidão transforma nossa vida. Liberta nosso coração amargurado. A gratidão quebra muralhas, a gratidão evita pecados.\nReclamamos por tudo!\nMas, e a gratidão?\nE a gratidão por tudo aquilo que Deus fez, pelos detalhes, pela generosidade da mesa farta, pelas amizades, pela Palavra de Deus ministrada aos corações, pela saúde de poder findar o ano na presença de Deus?!\nE a gratidão por lembrar que esse Deus enviou o Seu Filho para morrer na cruz, para que tenhamos a vida eterna?!\nE a gratidão pelas batalhas, pelas portas fechadas, por Deus dizer não e você depois olhar e dizer como foi cuidado por Deus?!\nPrecisamos mudar uma cultura de murmuração por uma cultura de gratidão.\nO que faremos agora é um ato de gratidão. É um ato de reconhecimento, de que pelo Corpo e Sangue de Cristo Jesus, nós fomos sarados.\nA Ceia do Senhor é a clara lembrança,de que no passado Deus fez por nós. De que no presente Deus faz por nós. De que o futuro está garantido, porque Deus assim garantiu, mediante a Sua Palavra e mediante o sacrifício de Seu Filho.\nEstamos reunidos em profunda gratidão.\nDaqueles dez, um voltou para agradecer.\nNove homens foram curados da lepra, mas um homem foi curado da lepra e teve naquele dia,  a salvação da sua alma.\nEstamos aqui para celebrar, que um dia, nós também, tivemos a nossa alma curada, resgatada, redimida e assim podemos entrar no novo ano, aguardando o retorno do nosso Salvador.\nPastor Gabriel Monteiro\nIBPS",
      "tamanho_texto": 3403,
      "url_blog": "https://pregacoesibps.blogspot.com/2026/01/lucas-1711-19.html",
      "url_youtube": "",
      "tags": [],
      "_metadados": {
        "ano_arquivo": 2026,
        "igreja": "",
        "processado_em": "2026-01-16T13:57:17.387072",
        "data_fonte": "fallback"
      },
      "id_unico": "2026_007",
      "metadados_biblicos": {
        "livro_principal": "Lucas",
        "texto_base": "Lucas 17:11-19",
        "total_referencias": 2,
        "referencias_titulo": 1,
        "referencias_conteudo": 1,
        "livros_mencionados": [
          "Lucas"
        ],
        "todas_referencias": [
          "Lucas 17:11-19",
          "Lucas 17:11-19"
        ]
      }
    }
  ],
  "relatorio_normalizacao": {
    "total_pregacoes": 7,
    "com_data": 6,
    "sem_data": 1,
    "com_pregador": 7,
    "sem_pregador": 0,
    "com_conteudo_valido": 7,
    "tamanho_medio": 7099,
    "tamanho_minimo": 3403,
    "tamanho_maximo": 8462,
    "por_ano": {
      "2026": 5,
      "2025": 2
    },
    "por_pregador": {
      "Gabriel Monteiro": 5,
      "Nélio Monteiro": 1,
      "Ryan Souza": 1
    },
    "por_tipo_pregador": {
      "oficial": 7
    },
    "sem_pregador_detalhes": [],
    "fontes_data": {
      "texto": 6,
      "fallback": 1
    }
  },
  "relatorio_biblico": {
    "total_pregacoes": 7,
    "com_livro_identificado": 7,
    "sem_livro": 0,
    "total_referencias_extraidas": 29,
    "media_referencias_por_pregacao": 4.142857142857143,
    "top_10_livros": [
      [
        "Mateus",
        4
      ],
      [
        "Salmos",
        1
      ],
      [
        "Apocalipse",
        1
      ],
      [
        "Lucas",
        1
      ]
    ]
  }
}